{"CODIGO_TRANSFORMADOR": "65003294", "MATRÍCULA CT": "A026169", "MATRÍCULA_TRANSFORMADOR": "E5742", "MATRÍCULA_CENSO": "", "DIRECCIÓN TRAFO": "CRA 21 # 42-04 LA LUCHA", "POTENCIA_NOMINAL": "50.0", "LEVANTAR_STATUS": "LEVANTAR", "COORDENADA_X": "987595.29", "COORDENADA_Y": "1732060.055", "CLIENTES": [{"MATRÍCULA CT": "A026169", "NIU": 18931889, "NIS_RAD_1": 1166674, "NIC": 1056827.0, "MEDIDOR": "3919744-MC965", "DIRECCION_CLIENTE": "CL 42  No. 20B -  50", "NOMBRE_CLIENTE": "AMELIA BOZON"}, {"MATRÍCULA CT": "A026169", "NIU": 30138833, "NIS_RAD_1": 9139726, "NIC": 8151058.0, "MEDIDOR": "23155807", "DIRECCION_CLIENTE": "CL SIN ASIGNAR CALLE  No. 0 -  0", "NOMBRE_CLIENTE": "ARMANDO LUIS RUMBO MARTINEZ"}, {"MATRÍCULA CT": "A026169", "NIU": 17653345, "NIS_RAD_1": 4354598, "NIC": 4322203.0, "MEDIDOR": "001012270-MC979", "DIRECCION_CLIENTE": "CL 42  No. 20D -  14", "NOMBRE_CLIENTE": "DANIEL CONSTANTE"}, {"MATRÍCULA CT": "A026169", "NIU": 17440626, "NIS_RAD_1": 1166635, "NIC": 1056814.0, "MEDIDOR": "31985355-MC164", "DIRECCION_CLIENTE": "CL 42  No. 20D -  2", "NOMBRE_CLIENTE": "ESTHER FRAGOSO"}, {"MATRÍCULA CT": "A026169", "NIU": 18148277, "NIS_RAD_1": 6022472, "NIC": 5891835.0, "MEDIDOR": "", "DIRECCION_CLIENTE": "CR 20D  No. CL 42 -  16", "NOMBRE_CLIENTE": "SARITA MOISES DANGON"}, {"MATRÍCULA CT": "A026169", "NIU": 19572721, "NIS_RAD_1": 8616548, "NIC": "", "MEDIDOR": "", "DIRECCION_CLIENTE": "CL 42  No. 20B -  9999", "NOMBRE_CLIENTE": ""}, {"MATRÍCULA CT": "A026169", "NIU": 17440631, "NIS_RAD_1": 1166665, "NIC": 1056824.0, "MEDIDOR": "773084-MC084", "DIRECCION_CLIENTE": "CL 42  No. 20B -  22", "NOMBRE_CLIENTE": "LUIS AGUADO"}, {"MATRÍCULA CT": "A026169", "NIU": 17440632, "NIS_RAD_1": 1166671, "NIC": 1056826.0, "MEDIDOR": "0000306-MC879", "DIRECCION_CLIENTE": "CL 42  No. 20B -  42", "NOMBRE_CLIENTE": "EMERITA CUENTAS"}, {"MATRÍCULA CT": "A026169", "NIU": 17440633, "NIS_RAD_1": 1166677, "NIC": 1056828.0, "MEDIDOR": "2022114822", "DIRECCION_CLIENTE": "CL 42  No. 20B -  76", "NOMBRE_CLIENTE": "SARA AGUAS DE FDEZ"}, {"MATRÍCULA CT": "A026169", "NIU": 17440634, "NIS_RAD_1": 1166680, "NIC": 1056829.0, "MEDIDOR": "4423115-MC879", "DIRECCION_CLIENTE": "CR 20D  No. CL 42 -  4", "NOMBRE_CLIENTE": "TOMASA BEATRIZ PACHECO CASTILLO"}], "TOTAL_CLIENTES": 10}