{"CODIGO_TRANSFORMADOR": "65014849", "MATRÍCULA CT": "2682L", "MATRÍCULA_TRANSFORMADOR": "2009M", "MATRÍCULA_CENSO": "A45112", "DIRECCIÓN TRAFO": "FINCA ANA DILIA", "POTENCIA_NOMINAL": "15.0", "LEVANTAR_STATUS": "NO LEVANTAR", "COORDENADA_X": "984431.907", "COORDENADA_Y": "1696861.169", "CLIENTES": [{"MATRÍCULA CT": "2682L", "NIU": 18267653, "NIS_RAD_1": 6219225, "NIC": 6210526.0, "MEDIDOR": "0000226842-MC957", "DIRECCION_CLIENTE": "CL PRINCIPAL  No. CR 7A -  46", "NOMBRE_CLIENTE": "YEISI BOBEA PEREZ"}], "TOTAL_CLIENTES": 1}