{"CODIGO_TRANSFORMADOR": "65728547", "MATRÍCULA CT": "5327E", "MATRÍCULA_TRANSFORMADOR": "4618E", "MATRÍCULA_CENSO": "A07225", "DIRECCIÓN TRAFO": "CLL 14 # 4C SUR-10", "POTENCIA_NOMINAL": "50.0", "LEVANTAR_STATUS": "NO LEVANTAR", "COORDENADA_X": "922243.541", "COORDENADA_Y": "1691687.762", "CLIENTES": [{"MATRÍCULA CT": "5327E", "NIU": 18444587, "NIS_RAD_1": 6463612, "NIC": 6325710.0, "MEDIDOR": "001193804-MC979", "DIRECCION_CLIENTE": "CR 4CSUR  No. CL 13A -  1", "NOMBRE_CLIENTE": "IVETH ALMANZO"}, {"MATRÍCULA CT": "5327E", "NIU": 18444591, "NIS_RAD_1": 6463624, "NIC": 6325714.0, "MEDIDOR": "11362147-MC941", "DIRECCION_CLIENTE": "CR 4CSUR  No. CL 13A -  15", "NOMBRE_CLIENTE": "OVANIS NAVARRO"}, {"MATRÍCULA CT": "5327E", "NIU": 18444602, "NIS_RAD_1": 6463657, "NIC": 6325725.0, "MEDIDOR": "0000256068-MC957", "DIRECCION_CLIENTE": "CR 4CSUR  No. CL 13A -  39", "NOMBRE_CLIENTE": "SAN MARTIN MALAMBO"}, {"MATRÍCULA CT": "5327E", "NIU": 18444603, "NIS_RAD_1": 6463660, "NIC": 6325726.0, "MEDIDOR": "001346782-MC979", "DIRECCION_CLIENTE": "CR 4CSUR  No. CL 13A -  45", "NOMBRE_CLIENTE": "CIELO HERRERA"}, {"MATRÍCULA CT": "5327E", "NIU": 18437770, "NIS_RAD_1": 6963588, "NIC": 6646923.0, "MEDIDOR": "11373547-MC941", "DIRECCION_CLIENTE": "CL 14  No. 4 SUR -  3", "NOMBRE_CLIENTE": "YUDIS M. YEPES SIERRA"}, {"MATRÍCULA CT": "5327E", "NIU": 18445416, "NIS_RAD_1": 6963592, "NIC": 6646924.0, "MEDIDOR": "11373549-MC941", "DIRECCION_CLIENTE": "CL 14  No. 4 SUR -  15", "NOMBRE_CLIENTE": "ELISA M. GUZMAN PLATA"}, {"MATRÍCULA CT": "5327E", "NIU": 19707190, "NIS_RAD_1": 8960253, "NIC": 7087314.0, "MEDIDOR": "", "DIRECCION_CLIENTE": "CR 4CSUR  No. 14 -  79", "NOMBRE_CLIENTE": "MANUEL NORIEGA BARRIOS"}, {"MATRÍCULA CT": "5327E", "NIU": 19715600, "NIS_RAD_1": 8967311, "NIC": 7090703.0, "MEDIDOR": "0023157-MCA50", "DIRECCION_CLIENTE": "CR 4CSUR  No. 14 -  39", "NOMBRE_CLIENTE": "CARMEN SAMPER"}, {"MATRÍCULA CT": "5327E", "NIU": 21391412, "NIS_RAD_1": 105584, "NIC": 1119784.0, "MEDIDOR": "12189366-MCA54", "DIRECCION_CLIENTE": "CR 1A  No. CL 15 -  41", "NOMBRE_CLIENTE": "ELENA. ROMERO. DE MANCO."}, {"MATRÍCULA CT": "5327E", "NIU": 21391454, "NIS_RAD_1": 105689, "NIC": 1119824.0, "MEDIDOR": "12183881-MCA54", "DIRECCION_CLIENTE": "CR 1A  No. CL 15 -  13", "NOMBRE_CLIENTE": "MALKA. GONZALEZ. OSPINA."}, {"MATRÍCULA CT": "5327E", "NIU": 21391458, "NIS_RAD_1": 105701, "NIC": 1119828.0, "MEDIDOR": "12189216-MCA54", "DIRECCION_CLIENTE": "CL 15  No. CR 1ASUR -  93", "NOMBRE_CLIENTE": "IGNACIO. VEGA."}, {"MATRÍCULA CT": "5327E", "NIU": 21391459, "NIS_RAD_1": 105704, "NIC": 1119829.0, "MEDIDOR": "12189215-MCA54", "DIRECCION_CLIENTE": "CL 15  No. CR 1ASUR -  91", "NOMBRE_CLIENTE": "WILLIAM ANDRES GARCIA."}, {"MATRÍCULA CT": "5327E", "NIU": 21391460, "NIS_RAD_1": 105707, "NIC": 1119830.0, "MEDIDOR": "2022079683", "DIRECCION_CLIENTE": "CL 15  No. CR 1ASUR -  77", "NOMBRE_CLIENTE": "NAIT. MONTENEGRO."}, {"MATRÍCULA CT": "5327E", "NIU": 21391465, "NIS_RAD_1": 105724, "NIC": 1119837.0, "MEDIDOR": "13093783-MCA55", "DIRECCION_CLIENTE": "CL 15  No. CR 1ASUR -  103", "NOMBRE_CLIENTE": "YENIS. PALACIO."}, {"MATRÍCULA CT": "5327E", "NIU": 21374842, "NIS_RAD_1": 41876, "NIC": 1099059.0, "MEDIDOR": "12006128-MCA20", "DIRECCION_CLIENTE": "CR 4CSUR  No. CL 13 -  53", "NOMBRE_CLIENTE": "DEIVIS E. VILLAREAL SOLANO"}, {"MATRÍCULA CT": "5327E", "NIU": 21374906, "NIS_RAD_1": 42013, "NIC": 1099195.0, "MEDIDOR": "12005853-MCA20", "DIRECCION_CLIENTE": "CL 13  No. CR 4DSUR -  16", "NOMBRE_CLIENTE": "OMAR DIAZ AREVALO"}, {"MATRÍCULA CT": "5327E", "NIU": 19868067, "NIS_RAD_1": 3410100, "NIC": 7162658.0, "MEDIDOR": "", "DIRECCION_CLIENTE": "CR 4CSUR  No. 12A -  3", "NOMBRE_CLIENTE": "YULIS FLOREZ"}, {"MATRÍCULA CT": "5327E", "NIU": 20038456, "NIS_RAD_1": 1873565, "NIC": 7260847.0, "MEDIDOR": "", "DIRECCION_CLIENTE": "CL 15  No. 1SUR -  113", "NOMBRE_CLIENTE": "IRIS MARTINEZ"}, {"MATRÍCULA CT": "5327E", "NIU": 18444586, "NIS_RAD_1": 6463609, "NIC": 6325709.0, "MEDIDOR": "12100679-MCA54", "DIRECCION_CLIENTE": "CR 4BSUR  No. CL 13B -  3", "NOMBRE_CLIENTE": "LORENA RAMIREZ MARTINEZ"}, {"MATRÍCULA CT": "5327E", "NIU": 18444593, "NIS_RAD_1": 6463630, "NIC": 6325716.0, "MEDIDOR": "11362145-MC941", "DIRECCION_CLIENTE": "CR 4CSUR  No. CL 13A -  27", "NOMBRE_CLIENTE": "EULIS NARVAEZ"}, {"MATRÍCULA CT": "5327E", "NIU": 21447417, "NIS_RAD_1": 505929, "NIC": 1358906.0, "MEDIDOR": "", "DIRECCION_CLIENTE": "CL 15  No. 1SUR -  101", "NOMBRE_CLIENTE": "CAROLAY. CHARRIS."}, {"MATRÍCULA CT": "5327E", "NIU": 19866930, "NIS_RAD_1": 3409896, "NIC": 7162590.0, "MEDIDOR": "", "DIRECCION_CLIENTE": "CL 13B  No. 4SUR -  20", "NOMBRE_CLIENTE": "MARIANA GOENAGA"}, {"MATRÍCULA CT": "5327E", "NIU": 18400647, "NIS_RAD_1": 6434986, "NIC": 6311835.0, "MEDIDOR": "12239978-MCA54", "DIRECCION_CLIENTE": "CR 4BSUR  No. 13B -  16", "NOMBRE_CLIENTE": "WALBER NARVAEZ CARRILLO"}, {"MATRÍCULA CT": "5327E", "NIU": 18444585, "NIS_RAD_1": 6463606, "NIC": 6325708.0, "MEDIDOR": "11364208-MC941", "DIRECCION_CLIENTE": "CR 4BSUR  No. CL 13B -  21", "NOMBRE_CLIENTE": "MELVIS MEZA"}, {"MATRÍCULA CT": "5327E", "NIU": 18444592, "NIS_RAD_1": 6463627, "NIC": 6325715.0, "MEDIDOR": "11362148-MC941", "DIRECCION_CLIENTE": "CR 4CSUR  No. CL 13A -  21", "NOMBRE_CLIENTE": "MONICA CONRADO"}, {"MATRÍCULA CT": "5327E", "NIU": 18403274, "NIS_RAD_1": 6435070, "NIC": 6311863.0, "MEDIDOR": "19200248-MCA59", "DIRECCION_CLIENTE": "CR 4CSUR  No. 14 -  3", "NOMBRE_CLIENTE": "MERLYS TOMAS MONSALVE"}, {"MATRÍCULA CT": "5327E", "NIU": 18403276, "NIS_RAD_1": 6435076, "NIC": 6311865.0, "MEDIDOR": "11364302-MC941", "DIRECCION_CLIENTE": "CR 4CSUR  No. 14 -  27", "NOMBRE_CLIENTE": "LIZETH ESCORCIA"}, {"MATRÍCULA CT": "5327E", "NIU": 18416002, "NIS_RAD_1": 6427665, "NIC": 6308406.0, "MEDIDOR": "11364201-MC941", "DIRECCION_CLIENTE": "CR 4BSUR  No. 13B -  9", "NOMBRE_CLIENTE": "ALVARO CELIN MEDINA"}, {"MATRÍCULA CT": "5327E", "NIU": 18400652, "NIS_RAD_1": 6435001, "NIC": 6311840.0, "MEDIDOR": "12239979-MCA54", "DIRECCION_CLIENTE": "CR 4BSUR  No. 13B -  70", "NOMBRE_CLIENTE": "LISBETH ALCAZAR SANDOVAL"}, {"MATRÍCULA CT": "5327E", "NIU": 18408521, "NIS_RAD_1": 6435301, "NIC": 6311940.0, "MEDIDOR": "11364301-MC941", "DIRECCION_CLIENTE": "CR 4CSUR  No. 14 -  33", "NOMBRE_CLIENTE": "VIRGINIA AGUILAR"}, {"MATRÍCULA CT": "5327E", "NIU": 21374861, "NIS_RAD_1": 41899, "NIC": 1099063.0, "MEDIDOR": "12006121-MCA20", "DIRECCION_CLIENTE": "CR 4CSUR  No. CL 13 -  23", "NOMBRE_CLIENTE": "ISABEL MARCHENA GUTIERREZ"}, {"MATRÍCULA CT": "5327E", "NIU": 18444601, "NIS_RAD_1": 6463654, "NIC": 6325724.0, "MEDIDOR": "2022102987", "DIRECCION_CLIENTE": "CR 4CSUR  No. CL 13A -  33", "NOMBRE_CLIENTE": "LINA MARTINEZ"}, {"MATRÍCULA CT": "5327E", "NIU": 18444597, "NIS_RAD_1": 6463642, "NIC": 6325720.0, "MEDIDOR": "11362146-MC941", "DIRECCION_CLIENTE": "CR 4CSUR  No. CL 13A -  9", "NOMBRE_CLIENTE": "SAN MARTIN MALAMBO"}, {"MATRÍCULA CT": "5327E", "NIU": 18444583, "NIS_RAD_1": 6463600, "NIC": 6325706.0, "MEDIDOR": "11373831-MC941", "DIRECCION_CLIENTE": "CR 4BSUR  No. CL 13B -  27", "NOMBRE_CLIENTE": "ANA HURTADO"}, {"MATRÍCULA CT": "5327E", "NIU": 18437769, "NIS_RAD_1": 6963584, "NIC": 6646922.0, "MEDIDOR": "11373548-MC941", "DIRECCION_CLIENTE": "CL 14  No. 4 SUR -  9", "NOMBRE_CLIENTE": "NURYS I MARIN CONRRADO"}, {"MATRÍCULA CT": "5327E", "NIU": 18408513, "NIS_RAD_1": 6435274, "NIC": 6311931.0, "MEDIDOR": "11373839-MC941", "DIRECCION_CLIENTE": "CR 4BSUR  No. 13B -  46", "NOMBRE_CLIENTE": "SANDRA ISABEL NORIEGA ESCORCIA"}, {"MATRÍCULA CT": "5327E", "NIU": 19706331, "NIS_RAD_1": 8960250, "NIC": 7087313.0, "MEDIDOR": "", "DIRECCION_CLIENTE": "CR 4CSUR  No. 14 -  58", "NOMBRE_CLIENTE": "JHON DIAZ ESTRADA"}, {"MATRÍCULA CT": "5327E", "NIU": 18444589, "NIS_RAD_1": 6463618, "NIC": 6325712.0, "MEDIDOR": "11373684-MC941", "DIRECCION_CLIENTE": "CR 4CSUR  No. 13A -  3", "NOMBRE_CLIENTE": "ANA CAMARGO"}, {"MATRÍCULA CT": "5327E", "NIU": 18416001, "NIS_RAD_1": 6427662, "NIC": 6308405.0, "MEDIDOR": "11364207-MC941", "DIRECCION_CLIENTE": "CR 4BSUR  No. 13B -  15", "NOMBRE_CLIENTE": "ELA POLO TOMAS"}, {"MATRÍCULA CT": "5327E", "NIU": 18400649, "NIS_RAD_1": 6434992, "NIC": 6311837.0, "MEDIDOR": "11361301-MC941", "DIRECCION_CLIENTE": "CR 4BSUR  No. 13B -  40", "NOMBRE_CLIENTE": "ZULMA BARCELO DE LA CRUZ"}, {"MATRÍCULA CT": "5327E", "NIU": 18400646, "NIS_RAD_1": 6434983, "NIC": 6311834.0, "MEDIDOR": "0000485860-MC957", "DIRECCION_CLIENTE": "CR 4BSUR  No. 13B -  10", "NOMBRE_CLIENTE": "VIRGINIA TETE ESCOBAR"}, {"MATRÍCULA CT": "5327E", "NIU": 18411100, "NIS_RAD_1": 6435367, "NIC": 6311962.0, "MEDIDOR": "11373834-MC941", "DIRECCION_CLIENTE": "CR 4BSUR  No. 13B -  52", "NOMBRE_CLIENTE": "MARIA TOMAS FERRER"}, {"MATRÍCULA CT": "5327E", "NIU": 18403258, "NIS_RAD_1": 6435022, "NIC": 6311847.0, "MEDIDOR": "11373685-MC941", "DIRECCION_CLIENTE": "CL 13B  No. 4SUR -  28", "NOMBRE_CLIENTE": "JHON NARVAEZ"}, {"MATRÍCULA CT": "5327E", "NIU": 18408514, "NIS_RAD_1": 6435277, "NIC": 6311932.0, "MEDIDOR": "001417184-MC979", "DIRECCION_CLIENTE": "CL 13B  No. 4SUR -  4", "NOMBRE_CLIENTE": "NARLIS ROCIO CARRILLO LECHUGA"}, {"MATRÍCULA CT": "5327E", "NIU": 18400650, "NIS_RAD_1": 6434995, "NIC": 6311838.0, "MEDIDOR": "11373832-MC941", "DIRECCION_CLIENTE": "CR 4BSUR  No. 13B -  58", "NOMBRE_CLIENTE": "IMERA SEGURA MIRANDA"}, {"MATRÍCULA CT": "5327E", "NIU": 18400651, "NIS_RAD_1": 6434998, "NIC": 6311839.0, "MEDIDOR": "11373540-MC941", "DIRECCION_CLIENTE": "CR 4BSUR  No. 13B -  64", "NOMBRE_CLIENTE": "ROCIO CABALLERO DE LA HOZ"}, {"MATRÍCULA CT": "5327E", "NIU": 19585148, "NIS_RAD_1": 8632251, "NIC": 7570827.0, "MEDIDOR": "12115510-MCA54", "DIRECCION_CLIENTE": "CL 14  No. 4BSUR -  4", "NOMBRE_CLIENTE": "YULEIDE MORA"}, {"MATRÍCULA CT": "5327E", "NIU": 18437134, "NIS_RAD_1": 6434749, "NIC": 6311756.0, "MEDIDOR": "11364300-MC941", "DIRECCION_CLIENTE": "CR 4CSUR  No. 14 -  21", "NOMBRE_CLIENTE": "MARLA ALMARALES RUIZ"}, {"MATRÍCULA CT": "5327E", "NIU": 21391388, "NIS_RAD_1": 105517, "NIC": 1119758.0, "MEDIDOR": "12189368-MCA54", "DIRECCION_CLIENTE": "CL 14  No. CR 1B -  22", "NOMBRE_CLIENTE": "KELLY. ALCAZA."}, {"MATRÍCULA CT": "5327E", "NIU": 21391390, "NIS_RAD_1": 105522, "NIC": 1119760.0, "MEDIDOR": "19202829-MCA54", "DIRECCION_CLIENTE": "CL 14  No. CR 1A -  40", "NOMBRE_CLIENTE": "JAVIER. PACHECO."}, {"MATRÍCULA CT": "5327E", "NIU": 21391406, "NIS_RAD_1": 105566, "NIC": 1119776.0, "MEDIDOR": "12183882-MCA54", "DIRECCION_CLIENTE": "CR 1A  No. CL 15 -  21", "NOMBRE_CLIENTE": "CAROL. PEREZ. MEZA."}, {"MATRÍCULA CT": "5327E", "NIU": 21391464, "NIS_RAD_1": 105721, "NIC": 1119836.0, "MEDIDOR": "12189119-MCA54", "DIRECCION_CLIENTE": "CL 15  No. CR 1 -  31", "NOMBRE_CLIENTE": "OLGA ESTHER. MIRANDA."}, {"MATRÍCULA CT": "5327E", "NIU": 21391457, "NIS_RAD_1": 105696, "NIC": 1119827.0, "MEDIDOR": "12183877-MCA54", "DIRECCION_CLIENTE": "CR 1A  No. CL 15 -  35", "NOMBRE_CLIENTE": "WILLIAM. SERRANO. NORIEGA."}, {"MATRÍCULA CT": "5327E", "NIU": 21391456, "NIS_RAD_1": 105693, "NIC": 1119825.0, "MEDIDOR": "12183883-MCA54", "DIRECCION_CLIENTE": "CR 1A  No. CL 15 -  25", "NOMBRE_CLIENTE": "JAIME. ALCAZAR. COTES."}, {"MATRÍCULA CT": "5327E", "NIU": 21391461, "NIS_RAD_1": 105710, "NIC": 1119831.0, "MEDIDOR": "12189110-MCA54", "DIRECCION_CLIENTE": "CL 15  No. CR 1ASUR -  83", "NOMBRE_CLIENTE": "ALEJANDRO. MEZA."}, {"MATRÍCULA CT": "5327E", "NIU": 21429257, "NIS_RAD_1": 457764, "NIC": 1342326.0, "MEDIDOR": "12223669-MCA54", "DIRECCION_CLIENTE": "CL 15  No. CR 1SUR -  85", "NOMBRE_CLIENTE": "VICTOR RODRIGUEZ RAMBAO"}, {"MATRÍCULA CT": "5327E", "NIU": 21391423, "NIS_RAD_1": 105611, "NIC": 1119792.0, "MEDIDOR": "12206176-MCA54", "DIRECCION_CLIENTE": "CL 15  No. CR 1A -  128", "NOMBRE_CLIENTE": "KELLY. SAMPER."}, {"MATRÍCULA CT": "5327E", "NIU": 21391453, "NIS_RAD_1": 105686, "NIC": 1119823.0, "MEDIDOR": "12200469-MCA54", "DIRECCION_CLIENTE": "CL 14  No. CR 1 -  50", "NOMBRE_CLIENTE": "ELIANA. FABREGAS."}, {"MATRÍCULA CT": "5327E", "NIU": 21435651, "NIS_RAD_1": 471907, "NIC": 1348278.0, "MEDIDOR": "23057887-MCA56", "DIRECCION_CLIENTE": "CR 1A  No. 13 -  30", "NOMBRE_CLIENTE": "LIBARDO JOSE AMADOR VARGAS"}, {"MATRÍCULA CT": "5327E", "NIU": 18445417, "NIS_RAD_1": 6963595, "NIC": 6646925.0, "MEDIDOR": "11373546-MC941", "DIRECCION_CLIENTE": "CL 14  No. 4 SUR -  21", "NOMBRE_CLIENTE": "ROCIO I. LONDOO TORRES"}, {"MATRÍCULA CT": "5327E", "NIU": 975105, "NIS_RAD_1": 471401, "NIC": 1348068.0, "MEDIDOR": "23057888-MCA56", "DIRECCION_CLIENTE": "CL 14  No. 1A -  2", "NOMBRE_CLIENTE": "JUAN DAVID PACHECO MATUTE"}, {"MATRÍCULA CT": "5327E", "NIU": 975148, "NIS_RAD_1": 471755, "NIC": 1348213.0, "MEDIDOR": "12239971-MCA54", "DIRECCION_CLIENTE": "CL 14  No. 1A -  5", "NOMBRE_CLIENTE": "VILMA ROSA PADILLA DOMINGUEZ"}, {"MATRÍCULA CT": "5327E", "NIU": 21391408, "NIS_RAD_1": 105575, "NIC": 1119780.0, "MEDIDOR": "12183927-MCA54", "DIRECCION_CLIENTE": "CR 1A  No. CL 15 -  29", "NOMBRE_CLIENTE": "FRANCISCO. PEREZ."}, {"MATRÍCULA CT": "5327E", "NIU": 17126021, "NIS_RAD_1": 2467539, "NIC": 2169570.0, "MEDIDOR": "0020261-MCA04", "DIRECCION_CLIENTE": "CR 1  No. 15 -  30", "NOMBRE_CLIENTE": "WILSON DOMINGUEZ POLO"}, {"MATRÍCULA CT": "5327E", "NIU": 18400648, "NIS_RAD_1": 6434989, "NIC": 6311836.0, "MEDIDOR": "11361300-MC941", "DIRECCION_CLIENTE": "CR 4BSUR  No. 13B -  34", "NOMBRE_CLIENTE": "EBYS CHARRIS VALERA"}, {"MATRÍCULA CT": "5327E", "NIU": 18403257, "NIS_RAD_1": 6435019, "NIC": 6311846.0, "MEDIDOR": "11373689-MC941", "DIRECCION_CLIENTE": "CL 13B  No. 4SUR -  16", "NOMBRE_CLIENTE": "DARIS HERRERA DURAN"}, {"MATRÍCULA CT": "5327E", "NIU": 18403275, "NIS_RAD_1": 6435073, "NIC": 6311864.0, "MEDIDOR": "11364304-MC941", "DIRECCION_CLIENTE": "CR 4CSUR  No. 14 -  9", "NOMBRE_CLIENTE": "ALIS PALACIO CASTILLA"}, {"MATRÍCULA CT": "5327E", "NIU": 18408515, "NIS_RAD_1": 6435280, "NIC": 6311933.0, "MEDIDOR": "001427717-MC979", "DIRECCION_CLIENTE": "CL 13B  No. 4SUR -  34", "NOMBRE_CLIENTE": "YANIRIS ESCORCIA"}, {"MATRÍCULA CT": "5327E", "NIU": 18398033, "NIS_RAD_1": 6434842, "NIC": 6311787.0, "MEDIDOR": "01687264-MC976", "DIRECCION_CLIENTE": "CR 4BSUR  No. 13B -  4", "NOMBRE_CLIENTE": "VERONICA CONTRERA PUA"}, {"MATRÍCULA CT": "5327E", "NIU": 18398034, "NIS_RAD_1": 6434845, "NIC": 6311788.0, "MEDIDOR": "11373688-MC941", "DIRECCION_CLIENTE": "CL 13B  No. 4SUR -  10", "NOMBRE_CLIENTE": "MELQUISEDEC OSORIO"}, {"MATRÍCULA CT": "5327E", "NIU": 18398036, "NIS_RAD_1": 6434851, "NIC": 6311790.0, "MEDIDOR": "11364303-MC941", "DIRECCION_CLIENTE": "CR 4CSUR  No. 14 -  15", "NOMBRE_CLIENTE": "YANETH PAYARES DE LA HOZ"}], "TOTAL_CLIENTES": 71}