{"CODIGO_TRANSFORMADOR": "65756633", "MATRÍCULA CT": "A027478", "MATRÍCULA_TRANSFORMADOR": "C3209", "MATRÍCULA_CENSO": "A04258", "DIRECCIÓN TRAFO": "CLL 19 CON CRA 17 37", "POTENCIA_NOMINAL": "50.0", "LEVANTAR_STATUS": "NO LEVANTAR", "LATITUD": "11.2388353", "LONGITUD": "-74.1985319", "CLIENTES": [{"MATRÍCULA CT": "A027478", "NIU": 19129535, "NIS_RAD_1": 1140730, "NIC": 1048179.0, "MEDIDOR": "10016786", "DIRECCION_CLIENTE": "CL 19  No. CR 16 -  23", "NOMBRE_CLIENTE": "FRANCISCO TABERA"}, {"MATRÍCULA CT": "A027478", "NIU": 19129544, "NIS_RAD_1": 1140739, "NIC": 1048182.0, "MEDIDOR": "23169769", "DIRECCION_CLIENTE": "CL 19  No. CR 16 -  1", "NOMBRE_CLIENTE": "EDUARDO MARIO ALBERICCI YOHAID"}, {"MATRÍCULA CT": "A027478", "NIU": 21303352, "NIS_RAD_1": 5488621, "NIC": 7929910.0, "MEDIDOR": "23070536-MCA56", "DIRECCION_CLIENTE": "CL 20  No. 17 -  15", "NOMBRE_CLIENTE": "JOLIANA PATRICIA LOPEZ IGLESIAS"}, {"MATRÍCULA CT": "A027478", "NIU": 21303353, "NIS_RAD_1": 5488622, "NIC": 7929911.0, "MEDIDOR": "23124682", "DIRECCION_CLIENTE": "CL 20  No. 17 -  15", "NOMBRE_CLIENTE": "JOLIANA PATRICIA LOPEZ IGLESIAS"}, {"MATRÍCULA CT": "A027478", "NIU": 19992907, "NIS_RAD_1": 1910107, "NIC": 7770285.0, "MEDIDOR": "23088310", "DIRECCION_CLIENTE": "CL 19  No. CR 16 -  1", "NOMBRE_CLIENTE": "EDUARDO MARIO ALBERICCI YOHAID"}, {"MATRÍCULA CT": "A027478", "NIU": 37039950, "NIS_RAD_1": 9248529, "NIC": 8301765.0, "MEDIDOR": "23184712", "DIRECCION_CLIENTE": "CL SIN ASIGNAR CALLE  No. 0 -  0", "NOMBRE_CLIENTE": "VICTORIA TERNERA"}, {"MATRÍCULA CT": "A027478", "NIU": 37039951, "NIS_RAD_1": 9248531, "NIC": 8301766.0, "MEDIDOR": "23184713", "DIRECCION_CLIENTE": "CL SIN ASIGNAR CALLE  No. 0 -  0", "NOMBRE_CLIENTE": "VICTORIA TERNERA"}, {"MATRÍCULA CT": "A027478", "NIU": 21355776, "NIS_RAD_1": 3795382, "NIC": 7976941.0, "MEDIDOR": "23070535-MCA56", "DIRECCION_CLIENTE": "CL 20  No. 17 -  15", "NOMBRE_CLIENTE": "JOLIANA PATRICIA LOPEZ IGLESIAS"}, {"MATRÍCULA CT": "A027478", "NIU": 19129440, "NIS_RAD_1": 1140547, "NIC": 1048118.0, "MEDIDOR": "10017227", "DIRECCION_CLIENTE": "CL 18  No. 16E -  64", "NOMBRE_CLIENTE": "Marina Esther Moreno De Pimienta"}, {"MATRÍCULA CT": "A027478", "NIU": 21424365, "NIS_RAD_1": 438777, "NIC": 1337951.0, "MEDIDOR": "12271707-MCA54", "DIRECCION_CLIENTE": "CL 20  No. 17 -  31", "NOMBRE_CLIENTE": "ELSY LEONOR CAMPO SANCHEZ"}, {"MATRÍCULA CT": "A027478", "NIU": 37036817, "NIS_RAD_1": 9255430, "NIC": 8310474.0, "MEDIDOR": "23184711", "DIRECCION_CLIENTE": "CL SIN ASIGNAR CALLE  No. 0 -  0", "NOMBRE_CLIENTE": "VICTORIA TATIANA TERNERA MERCADO"}, {"MATRÍCULA CT": "A027478", "NIU": 19993161, "NIS_RAD_1": 1910114, "NIC": 7770292.0, "MEDIDOR": "23106275", "DIRECCION_CLIENTE": "CL 19  No. CR 16 -  1", "NOMBRE_CLIENTE": "EDUARDO MARIO ALBERICCI YOHAID"}, {"MATRÍCULA CT": "A027478", "NIU": 19992092, "NIS_RAD_1": 1910104, "NIC": 7770284.0, "MEDIDOR": "23076995", "DIRECCION_CLIENTE": "CL 19  No. CR 16 -  1", "NOMBRE_CLIENTE": "EDUARDO MARIO ALBERICCI YOHAID"}, {"MATRÍCULA CT": "A027478", "NIU": 17354027, "NIS_RAD_1": 1140691, "NIC": 1048166.0, "MEDIDOR": "2022016749", "DIRECCION_CLIENTE": "CL 19  No. 17 -  9", "NOMBRE_CLIENTE": "JUANA VALDERRAMA"}, {"MATRÍCULA CT": "A027478", "NIU": 17372831, "NIS_RAD_1": 1094278, "NIC": 1032695.0, "MEDIDOR": "1070709", "DIRECCION_CLIENTE": "CR 17  No. CL 18 -  36", "NOMBRE_CLIENTE": "CARMELINA CASTEBLANCO"}, {"MATRÍCULA CT": "A027478", "NIU": 17354033, "NIS_RAD_1": 1140709, "NIC": 1048172.0, "MEDIDOR": "1502735", "DIRECCION_CLIENTE": "CL 19  No. CR 16E -  17", "NOMBRE_CLIENTE": "JOSE A MORENO"}, {"MATRÍCULA CT": "A027478", "NIU": 19992900, "NIS_RAD_1": 1910111, "NIC": 7770289.0, "MEDIDOR": "23116947", "DIRECCION_CLIENTE": "CL 19  No. CR 16 -  1", "NOMBRE_CLIENTE": "EDUARDO MARIO ALBERICCI YOHAID"}, {"MATRÍCULA CT": "A027478", "NIU": 17354028, "NIS_RAD_1": 1140694, "NIC": 1048167.0, "MEDIDOR": "20007251", "DIRECCION_CLIENTE": "CR 17  No. CL 18 -  26", "NOMBRE_CLIENTE": "ANA CASTERBLANCO"}, {"MATRÍCULA CT": "A027478", "NIU": 17354030, "NIS_RAD_1": 1140700, "NIC": 7856238.0, "MEDIDOR": "207325-MC960", "DIRECCION_CLIENTE": "CL 19  No. CR 16E -  53", "NOMBRE_CLIENTE": "ALFREDO ANTONIO FERREIRA MEJIA"}, {"MATRÍCULA CT": "A027478", "NIU": 17354023, "NIS_RAD_1": 1140679, "NIC": 1048162.0, "MEDIDOR": "10034514-MCA50", "DIRECCION_CLIENTE": "CL 20  No. 17 -  37", "NOMBRE_CLIENTE": "CESAR TERNERA S."}, {"MATRÍCULA CT": "A027478", "NIU": 19992905, "NIS_RAD_1": 1910108, "NIC": 7770288.0, "MEDIDOR": "20006409", "DIRECCION_CLIENTE": "CL 19  No. CR 16 -  1", "NOMBRE_CLIENTE": "EDUARDO MARIO ALBERICCI YOHAID"}, {"MATRÍCULA CT": "A027478", "NIU": 18375953, "NIS_RAD_1": 1140676, "NIC": 1048161.0, "MEDIDOR": "23106382", "DIRECCION_CLIENTE": "CL 20  No. 17 -  49", "NOMBRE_CLIENTE": "JORGE ELIECER MEZA BARRERA"}, {"MATRÍCULA CT": "A027478", "NIU": 19992911, "NIS_RAD_1": 1910113, "NIC": 7770290.0, "MEDIDOR": "23106374", "DIRECCION_CLIENTE": "CL 19  No. CR 16 -  1", "NOMBRE_CLIENTE": "MANUEL CANTILLO RUIDIAZ"}, {"MATRÍCULA CT": "A027478", "NIU": 19992884, "NIS_RAD_1": 1910115, "NIC": 7770295.0, "MEDIDOR": "23106274", "DIRECCION_CLIENTE": "CL 19  No. CR 16 -  1", "NOMBRE_CLIENTE": "FRANKLYN MANUEL SANTIAGO RETAMOSO"}, {"MATRÍCULA CT": "A027478", "NIU": 21355775, "NIS_RAD_1": 3795379, "NIC": 7976938.0, "MEDIDOR": "23114934", "DIRECCION_CLIENTE": "CL 20  No. 17 -  15", "NOMBRE_CLIENTE": "JOLIANA PATRICIA LOPEZ IGLESIAS"}, {"MATRÍCULA CT": "A027478", "NIU": 21330084, "NIS_RAD_1": 5741430, "NIC": 1108635.0, "MEDIDOR": "23106379", "DIRECCION_CLIENTE": "CL 20  No. 17 -  49", "NOMBRE_CLIENTE": "JORGE ELIECER MEZA BARRERA"}, {"MATRÍCULA CT": "A027478", "NIU": 17354022, "NIS_RAD_1": 1140673, "NIC": 1048160.0, "MEDIDOR": "23129950", "DIRECCION_CLIENTE": "CL 19  No. 17 -  59", "NOMBRE_CLIENTE": "LAURA MARIA USUGA VARELA"}, {"MATRÍCULA CT": "A027478", "NIU": 17354035, "NIS_RAD_1": 1140715, "NIC": 1048174.0, "MEDIDOR": "93349-MC961", "DIRECCION_CLIENTE": "CL 20  No.    16E -  5", "NOMBRE_CLIENTE": "OTONIEL ENRIQUE RINCONES GOMEZ"}, {"MATRÍCULA CT": "A027478", "NIU": 19129538, "NIS_RAD_1": 1140733, "NIC": 1048180.0, "MEDIDOR": "10024815", "DIRECCION_CLIENTE": "CL 19  No. CR 16 -  11", "NOMBRE_CLIENTE": "EFRAIN CAMPO GOMEZ"}, {"MATRÍCULA CT": "A027478", "NIU": 17354031, "NIS_RAD_1": 1140703, "NIC": 1048170.0, "MEDIDOR": "93273-MC960", "DIRECCION_CLIENTE": "CL 20  No. 16E -  37", "NOMBRE_CLIENTE": "MANUEL FRANCISCO SOLANO"}, {"MATRÍCULA CT": "A027478", "NIU": 19129541, "NIS_RAD_1": 1140736, "NIC": 1048181.0, "MEDIDOR": "10005579", "DIRECCION_CLIENTE": "CL 19  No. CR 16 -  3", "NOMBRE_CLIENTE": "ANA MARIA ILLIDGE"}, {"MATRÍCULA CT": "A027478", "NIU": 30105220, "NIS_RAD_1": 9072525, "NIC": 8067706.0, "MEDIDOR": "1070481", "DIRECCION_CLIENTE": "CL SIN ASIGNAR CALLE  No. 0 -  0", "NOMBRE_CLIENTE": "ADRIANA TRUJILLO CASTRO"}, {"MATRÍCULA CT": "A027478", "NIU": 30145864, "NIS_RAD_1": 9147192, "NIC": 8162518.0, "MEDIDOR": "23163471", "DIRECCION_CLIENTE": "CL SIN ASIGNAR CALLE  No. 0 -  0", "NOMBRE_CLIENTE": "LEONOR CONSUELO GOMEZ"}, {"MATRÍCULA CT": "A027478", "NIU": 17354024, "NIS_RAD_1": 1140682, "NIC": 1048163.0, "MEDIDOR": "12277109-MCA54", "DIRECCION_CLIENTE": "CL 20  No. 17 -  31", "NOMBRE_CLIENTE": "ELSY LEONOR CAMPO SANCHEZ"}, {"MATRÍCULA CT": "A027478", "NIU": 17354025, "NIS_RAD_1": 1140685, "NIC": 1048164.0, "MEDIDOR": "23114932", "DIRECCION_CLIENTE": "CL 20  No. 17 -  15", "NOMBRE_CLIENTE": "JOLIANA PATRICIA LOPEZ IGLESIAS"}, {"MATRÍCULA CT": "A027478", "NIU": 17354029, "NIS_RAD_1": 1140697, "NIC": 1048168.0, "MEDIDOR": "93600-MC960", "DIRECCION_CLIENTE": "CL 19  No. CR 16E -  59", "NOMBRE_CLIENTE": "MARIA LUISA PALMERA CASTELBLANCO"}, {"MATRÍCULA CT": "A027478", "NIU": 17354032, "NIS_RAD_1": 1140706, "NIC": 7725826.0, "MEDIDOR": "23122189", "DIRECCION_CLIENTE": "CL 20  No. CR 16E -  31", "NOMBRE_CLIENTE": "MARITZA DEL CARMEN FONTALVO DE LA HOZ"}], "TOTAL_CLIENTES": 37}