{"CODIGO_TRANSFORMADOR": "65775669", "MATRÍCULA CT": "A036635", "MATRÍCULA_TRANSFORMADOR": "H2488", "MATRÍCULA_CENSO": "A25564", "DIRECCIÓN TRAFO": "CL 45  N° 35 - 37", "POTENCIA_NOMINAL": "25.0", "LEVANTAR_STATUS": "NO LEVANTAR", "LATITUD": "10.9788675", "LONGITUD": "-74.7884836", "MODELO": "SIEMENS", "TIPO CT": "Distribucion Tipo Poste", "TIPO CONEXION": "MONOFASICO BIFILAR", "CLIENTES": [{"MATRÍCULA CT": "A036635", "NIU": 20002722, "NIS_RAD_1": 1918153, "NIC": 7785673.0, "MEDIDOR": "2022136731", "DIRECCION_CLIENTE": "CL 45  No. 35 -  37", "NOMBRE_CLIENTE": "CL 45 35 37 CHIQUINQUIRA PEPSI"}, {"MATRÍCULA CT": "A036635", "NIU": 20001709, "NIS_RAD_1": 1918172, "NIC": 7785699.0, "MEDIDOR": "12217844-MCA54", "DIRECCION_CLIENTE": "CL 45  No. 35 -  37", "NOMBRE_CLIENTE": "CL 45 35 37 CHIQUINQUIRA PEPSI"}, {"MATRÍCULA CT": "A036635", "NIU": 20001731, "NIS_RAD_1": 1918178, "NIC": 7785706.0, "MEDIDOR": "001403935-MC988", "DIRECCION_CLIENTE": "CL 45  No. 35 -  37", "NOMBRE_CLIENTE": "CL 45 35 37 CHIQUINQUIRA PEPSI"}, {"MATRÍCULA CT": "A036635", "NIU": 20001781, "NIS_RAD_1": 1918125, "NIC": 7785559.0, "MEDIDOR": "2022136734", "DIRECCION_CLIENTE": "CL 45  No. 35 -  37", "NOMBRE_CLIENTE": "CL 45 35 37 CHIQUINQUIRA PESI"}, {"MATRÍCULA CT": "A036635", "NIU": 20001949, "NIS_RAD_1": 1918176, "NIC": 7785702.0, "MEDIDOR": "001403972-MC988", "DIRECCION_CLIENTE": "CL 45  No. 35 -  37", "NOMBRE_CLIENTE": "CL 45 35 37 CHIQUINQUIRA PEPSI"}, {"MATRÍCULA CT": "A036635", "NIU": 19999584, "NIS_RAD_1": 1918169, "NIC": 7785693.0, "MEDIDOR": "2022136732", "DIRECCION_CLIENTE": "CL 45  No. 35 -  37", "NOMBRE_CLIENTE": "CL 45 35 37 CHIQUINQUIRA PEPSI"}, {"MATRÍCULA CT": "A036635", "NIU": 20002303, "NIS_RAD_1": 1918166, "NIC": 7785688.0, "MEDIDOR": "2022136730", "DIRECCION_CLIENTE": "CL 45  No. 35 -  37", "NOMBRE_CLIENTE": "CL 45 35 37 CHIQUINQUIRA PEPSI"}, {"MATRÍCULA CT": "A036635", "NIU": 20002448, "NIS_RAD_1": 1918175, "NIC": 7785701.0, "MEDIDOR": "2022083339", "DIRECCION_CLIENTE": "CL 45  No. 35 -  37", "NOMBRE_CLIENTE": "CL 45 35 37 CHIQUINQUIRA PEPSI"}, {"MATRÍCULA CT": "A036635", "NIU": 20000070, "NIS_RAD_1": 1918148, "NIC": 7785671.0, "MEDIDOR": "12230306-MCA54", "DIRECCION_CLIENTE": "CL 45  No. 35 -  37", "NOMBRE_CLIENTE": "CL 45 35 37 CHIQUINQUIRA PEPSI"}, {"MATRÍCULA CT": "A036635", "NIU": 20001349, "NIS_RAD_1": 1918136, "NIC": 7785663.0, "MEDIDOR": "2022137081", "DIRECCION_CLIENTE": "CL 45  No. 35 -  37", "NOMBRE_CLIENTE": "CL 45 35 37 CHIQUINQUIRA PEPSI"}, {"MATRÍCULA CT": "A036635", "NIU": 20001385, "NIS_RAD_1": 1918168, "NIC": 7785691.0, "MEDIDOR": "001403962-MC988", "DIRECCION_CLIENTE": "CL 45  No. 35 -  37", "NOMBRE_CLIENTE": "CL 45 35 37 CHIQUINQUIRA PEPSI"}, {"MATRÍCULA CT": "A036635", "NIU": 20001411, "NIS_RAD_1": 1918154, "NIC": 7785676.0, "MEDIDOR": "12229374-MCA54", "DIRECCION_CLIENTE": "CL 45  No. 35 -  37", "NOMBRE_CLIENTE": "CL 45 35 37 CHIQUINQUIRA PEPSI"}, {"MATRÍCULA CT": "A036635", "NIU": 20002351, "NIS_RAD_1": 1918170, "NIC": 7785694.0, "MEDIDOR": "2022136733", "DIRECCION_CLIENTE": "CL 45  No. 35 -  37", "NOMBRE_CLIENTE": "EDGAR HERNANDO GALVIS VILLAMIZAR"}, {"MATRÍCULA CT": "A036635", "NIU": 20001619, "NIS_RAD_1": 1918161, "NIC": 7785686.0, "MEDIDOR": "12230884-MCA54", "DIRECCION_CLIENTE": "CL 45  No. 35 -  37", "NOMBRE_CLIENTE": "CL 45 35 37 CHIQUINQUIRA PEPSI"}, {"MATRÍCULA CT": "A036635", "NIU": 20002541, "NIS_RAD_1": 1918126, "NIC": 7785632.0, "MEDIDOR": "10002102-MCA50", "DIRECCION_CLIENTE": "CL 45  No. 35 -  37", "NOMBRE_CLIENTE": "CL 45 35 37 CHIQUINQUIRA PEPSI"}, {"MATRÍCULA CT": "A036635", "NIU": 20001183, "NIS_RAD_1": 1918135, "NIC": 7785660.0, "MEDIDOR": "2022083340", "DIRECCION_CLIENTE": "CL 45  No. 35 -  37", "NOMBRE_CLIENTE": "CL 45 35 37 CHIQUINQUIRA PEPSI"}, {"MATRÍCULA CT": "A036635", "NIU": 20002474, "NIS_RAD_1": 1918128, "NIC": 7785635.0, "MEDIDOR": "12214196-MCA54", "DIRECCION_CLIENTE": "CL 45  No. 35 -  37", "NOMBRE_CLIENTE": "CL 45 35 37 CHIQUINQUIRA PEPSI"}, {"MATRÍCULA CT": "A036635", "NIU": 20000393, "NIS_RAD_1": 1918160, "NIC": 7785685.0, "MEDIDOR": "001403940-MC988", "DIRECCION_CLIENTE": "CL 45  No. 35 -  37", "NOMBRE_CLIENTE": "CL 45 35 37 CHIQUINQUIRA PEPSI"}, {"MATRÍCULA CT": "A036635", "NIU": 20001708, "NIS_RAD_1": 1918167, "NIC": 7785689.0, "MEDIDOR": "2022136735", "DIRECCION_CLIENTE": "CL 45  No. 35 -  37", "NOMBRE_CLIENTE": "CL 45 35 37 CHIQUINQUIRA PEPSI"}, {"MATRÍCULA CT": "A036635", "NIU": 20002400, "NIS_RAD_1": 1918179, "NIC": "", "MEDIDOR": "", "DIRECCION_CLIENTE": "CL 45  No. 35 -  37", "NOMBRE_CLIENTE": ""}, {"MATRÍCULA CT": "A036635", "NIU": 19999828, "NIS_RAD_1": 1918156, "NIC": 7785677.0, "MEDIDOR": "2022137082", "DIRECCION_CLIENTE": "CL 45  No. 35 -  37", "NOMBRE_CLIENTE": "CL 45 35 37 CHIQUINQUIRA PEPSI"}, {"MATRÍCULA CT": "A036635", "NIU": 20001337, "NIS_RAD_1": 1918137, "NIC": 7785669.0, "MEDIDOR": "12214033-MCA54", "DIRECCION_CLIENTE": "CL 45  No. 35 -  37", "NOMBRE_CLIENTE": "CL 45 35 37 CHIQUINQUIRA PEPSI"}, {"MATRÍCULA CT": "A036635", "NIU": 20052939, "NIS_RAD_1": 1969815, "NIC": 7791353.0, "MEDIDOR": "290722-MC989", "DIRECCION_CLIENTE": "CL 45  No. 36 -  41", "NOMBRE_CLIENTE": "DISTRITO ESPECIAL, INDUSTRIAL Y PORTUARIO DE BARRANQUILLA"}, {"MATRÍCULA CT": "A036635", "NIU": 20002395, "NIS_RAD_1": 1918133, "NIC": 7785649.0, "MEDIDOR": "10002101-MCA50", "DIRECCION_CLIENTE": "CL 45  No. 35 -  37", "NOMBRE_CLIENTE": "CL 45 35 37 CHIQUINQUIRA PEPSI"}, {"MATRÍCULA CT": "A036635", "NIU": 20000527, "NIS_RAD_1": 1918130, "NIC": 7785646.0, "MEDIDOR": "10010802-MCA50", "DIRECCION_CLIENTE": "CL 45  No. 35 -  37", "NOMBRE_CLIENTE": "CL 45 5 37 CHIQUINQUIRA PEPSI"}, {"MATRÍCULA CT": "A036635", "NIU": 19999651, "NIS_RAD_1": 1918177, "NIC": 7785704.0, "MEDIDOR": "2022143847", "DIRECCION_CLIENTE": "CL 45  No. 35 -  37", "NOMBRE_CLIENTE": "CL 45 35 37 CHIQUINQUIRA PEPSI"}, {"MATRÍCULA CT": "A036635", "NIU": 20001350, "NIS_RAD_1": 1918157, "NIC": 7785679.0, "MEDIDOR": "10010829-MCA50", "DIRECCION_CLIENTE": "CL 45  No. 35 -  37", "NOMBRE_CLIENTE": "CL 45 35 37 CHIQUINQUIRA PEPSI"}, {"MATRÍCULA CT": "A036635", "NIU": 20000512, "NIS_RAD_1": 1918149, "NIC": 7785672.0, "MEDIDOR": "2022137080", "DIRECCION_CLIENTE": "CL 45  No. 35 -  37", "NOMBRE_CLIENTE": "CL 45 35 37 CHIQUINQUIRA PEPSI"}, {"MATRÍCULA CT": "A036635", "NIU": 19999577, "NIS_RAD_1": 1918163, "NIC": 7785687.0, "MEDIDOR": "2022143844", "DIRECCION_CLIENTE": "CL 45  No. 35 -  37", "NOMBRE_CLIENTE": "CL 45 35 37 CHIQUINQUIRA PEPSI"}], "TOTAL_CLIENTES": 29}