{"CODIGO_TRANSFORMADOR": "65778473", "MATRÍCULA CT": "A066821", "MATRÍCULA_TRANSFORMADOR": "H1230", "MATRÍCULA_CENSO": "A43253", "DIRECCIÓN TRAFO": "CALLE 98C N° 1E - 225", "POTENCIA_NOMINAL": "225.0", "LEVANTAR_STATUS": "NO LEVANTAR", "LATITUD": "10.9358499", "LONGITUD": "-74.829033", "MODELO": "INGEMERC LTDA", "TIPO CT": "Tipo Interiores de Edificaciones", "TIPO CONEXION": "TRIFASICO", "CLIENTES": [{"MATRÍCULA CT": "A066821", "NIU": 20050534, "NIS_RAD_1": 1962165, "NIC": 7788405.0, "MEDIDOR": "1502833751-MC981", "DIRECCION_CLIENTE": "CL 98C  No. 1E -  225", "NOMBRE_CLIENTE": "C 98C 1E 225 ALUMBRADO PUBLICO"}, {"MATRÍCULA CT": "A066821", "NIU": 20050540, "NIS_RAD_1": 1962164, "NIC": 7788404.0, "MEDIDOR": "1502833814-MC981", "DIRECCION_CLIENTE": "CL 98C  No. 1E -  225", "NOMBRE_CLIENTE": "CL 98C 1E 225 SALON COMUNAL"}, {"MATRÍCULA CT": "A066821", "NIU": 20087774, "NIS_RAD_1": 1366170, "NIC": 7815554.0, "MEDIDOR": "63222379-MC983", "DIRECCION_CLIENTE": "CL 98C  No. 1E -  225", "NOMBRE_CLIENTE": "DISTRITO ESPECIAL, INDUSTRIAL Y PORTUARIO DE BARRANQUILLA"}, {"MATRÍCULA CT": "A066821", "NIU": 20043660, "NIS_RAD_1": 3520907, "NIC": 7715631.0, "MEDIDOR": "", "DIRECCION_CLIENTE": "CL 98C  No. 1E -  225", "NOMBRE_CLIENTE": "Sin definir LAS GARDENIAS SEGE 1"}], "TOTAL_CLIENTES": 4}