{"CODIGO_TRANSFORMADOR": "65781232", "MATRÍCULA CT": "A070578", "MATRÍCULA_TRANSFORMADOR": "1520Q", "MATRÍCULA_CENSO": "A34479", "DIRECCIÓN TRAFO": "ENTRADA PPAL A SAN PEDRO DE LA SIERRA", "POTENCIA_NOMINAL": "50.0", "LEVANTAR_STATUS": "NO LEVANTAR", "CLIENTES": [{"MATRÍCULA CT": "A070578", "NIU": 18460032, "NIS_RAD_1": 6954121, "NIC": 6642861.0, "MEDIDOR": "001258484-MC979", "DIRECCION_CLIENTE": "CL 1  No. CR 2 -  697", "NOMBRE_CLIENTE": "JAIRO CUVIDES"}, {"MATRÍCULA CT": "A070578", "NIU": 18460035, "NIS_RAD_1": 6954127, "NIC": 6642862.0, "MEDIDOR": "0026905-MC942", "DIRECCION_CLIENTE": "CL 1  No. CR 2 -  699", "NOMBRE_CLIENTE": "SILFREDO ALZATE"}, {"MATRÍCULA CT": "A070578", "NIU": 19591649, "NIS_RAD_1": 8438558, "NIC": 7039257.0, "MEDIDOR": "0000226860-MC957", "DIRECCION_CLIENTE": "CL 1  No. CR 2 -  158", "NOMBRE_CLIENTE": "HERIBERTO COGOLLO"}, {"MATRÍCULA CT": "A070578", "NIU": 18981021, "NIS_RAD_1": 8143879, "NIC": 6947884.0, "MEDIDOR": "0176105-MC942", "DIRECCION_CLIENTE": "CL 1  No. CR 2 -  144", "NOMBRE_CLIENTE": "MARLENE MARIN CARDONA"}, {"MATRÍCULA CT": "A070578", "NIU": 18492378, "NIS_RAD_1": 6982482, "NIC": 6655262.0, "MEDIDOR": "11729033-MC941", "DIRECCION_CLIENTE": "CL 1  No. CR 2 -  148", "NOMBRE_CLIENTE": "FABIOLA HINCAPIE"}, {"MATRÍCULA CT": "A070578", "NIU": 21231879, "NIS_RAD_1": 4947670, "NIC": 7394819.0, "MEDIDOR": "12170340-MCA54", "DIRECCION_CLIENTE": "CL 1  No. CR 2 -  179", "NOMBRE_CLIENTE": "YURLADIS MARIO QUINTERO"}, {"MATRÍCULA CT": "A070578", "NIU": 21231923, "NIS_RAD_1": 4947714, "NIC": 7394841.0, "MEDIDOR": "12170339-MCA54", "DIRECCION_CLIENTE": "CL 1  No. CR 2 -  190", "NOMBRE_CLIENTE": "RICARDO COGOLLO COGOLLO"}, {"MATRÍCULA CT": "A070578", "NIU": 21231925, "NIS_RAD_1": 4947716, "NIC": 7394842.0, "MEDIDOR": "2022050793", "DIRECCION_CLIENTE": "CL 1  No. CR 2 -  188", "NOMBRE_CLIENTE": "NARLY SERRANO SERRANO"}, {"MATRÍCULA CT": "A070578", "NIU": 21231927, "NIS_RAD_1": 4947718, "NIC": 7394843.0, "MEDIDOR": "12173198-MCA54", "DIRECCION_CLIENTE": "CL 1  No. CR 2 -  181", "NOMBRE_CLIENTE": "LEONARDO MUOZ"}, {"MATRÍCULA CT": "A070578", "NIU": 19891868, "NIS_RAD_1": 3428204, "NIC": 7171058.0, "MEDIDOR": "12173196-MCA54", "DIRECCION_CLIENTE": "CL 1  No. CR 2 -  182", "NOMBRE_CLIENTE": "JOSE DEL CARMEN SERRANO MALDONADO"}, {"MATRÍCULA CT": "A070578", "NIU": 30171467, "NIS_RAD_1": 9196321, "NIC": 8244590.0, "MEDIDOR": "2022020617", "DIRECCION_CLIENTE": "CL SIN ASIGNAR CALLE  No. 0 -  0", "NOMBRE_CLIENTE": "JOSE SEBASTIAN GUZMAN"}, {"MATRÍCULA CT": "A070578", "NIU": 30171469, "NIS_RAD_1": 9196769, "NIC": 8244985.0, "MEDIDOR": "2022020610", "DIRECCION_CLIENTE": "CL SIN ASIGNAR CALLE  No. 0 -  0", "NOMBRE_CLIENTE": "EDUIN SANGUINEO"}, {"MATRÍCULA CT": "A070578", "NIU": 30171470, "NIS_RAD_1": 9196765, "NIC": 8244983.0, "MEDIDOR": "2022020608", "DIRECCION_CLIENTE": "CL SIN ASIGNAR CALLE  No. 0 -  0", "NOMBRE_CLIENTE": "GLADIS PEREZ NAVARRO"}, {"MATRÍCULA CT": "A070578", "NIU": 30172888, "NIS_RAD_1": 9196775, "NIC": 8244988.0, "MEDIDOR": "2022121609", "DIRECCION_CLIENTE": "CL SIN ASIGNAR CALLE  No. 0 -  0", "NOMBRE_CLIENTE": "ISABEL CADENA"}, {"MATRÍCULA CT": "A070578", "NIU": 30172890, "NIS_RAD_1": 9196777, "NIC": 8244989.0, "MEDIDOR": "2022121610", "DIRECCION_CLIENTE": "CL SIN ASIGNAR CALLE  No. 0 -  0", "NOMBRE_CLIENTE": "AYARID HERNANDEZ CADENA"}, {"MATRÍCULA CT": "A070578", "NIU": 30172891, "NIS_RAD_1": 9196779, "NIC": 8244990.0, "MEDIDOR": "2022121616", "DIRECCION_CLIENTE": "CL SIN ASIGNAR CALLE  No. 0 -  0", "NOMBRE_CLIENTE": "DIEGO GIRALDO"}, {"MATRÍCULA CT": "A070578", "NIU": 30171466, "NIS_RAD_1": 9196317, "NIC": 8244588.0, "MEDIDOR": "2022020611", "DIRECCION_CLIENTE": "CL SIN ASIGNAR CALLE  No. 0 -  0", "NOMBRE_CLIENTE": "JOSE SEBASTIAN GUZMAN"}, {"MATRÍCULA CT": "A070578", "NIU": 30171468, "NIS_RAD_1": 9196319, "NIC": 8244589.0, "MEDIDOR": "2022020609", "DIRECCION_CLIENTE": "CL SIN ASIGNAR CALLE  No. 0 -  0", "NOMBRE_CLIENTE": "JOSE SEBASTIAN GUZMAN"}, {"MATRÍCULA CT": "A070578", "NIU": 30172927, "NIS_RAD_1": 9196315, "NIC": 8244587.0, "MEDIDOR": "2022118641", "DIRECCION_CLIENTE": "CL SIN ASIGNAR CALLE  No. 0 -  0", "NOMBRE_CLIENTE": "BERNAVEL SERRANO"}, {"MATRÍCULA CT": "A070578", "NIU": 30172777, "NIS_RAD_1": 9196311, "NIC": 8244585.0, "MEDIDOR": "2022121615", "DIRECCION_CLIENTE": "CL SIN ASIGNAR CALLE  No. 0 -  0", "NOMBRE_CLIENTE": "GILDARDO PADIERNA HERNANDEZ"}, {"MATRÍCULA CT": "A070578", "NIU": 30173585, "NIS_RAD_1": 9196313, "NIC": 8244586.0, "MEDIDOR": "2022121613", "DIRECCION_CLIENTE": "CL SIN ASIGNAR CALLE  No. 0 -  0", "NOMBRE_CLIENTE": "TANIA TAFUR PEREZ"}, {"MATRÍCULA CT": "A070578", "NIU": 17499894, "NIS_RAD_1": 3800286, "NIC": 3800286.0, "MEDIDOR": "23142128", "DIRECCION_CLIENTE": "CL 1  No. CR 2 -  104", "NOMBRE_CLIENTE": "Sin definir PARCELA LA MARITZA"}, {"MATRÍCULA CT": "A070578", "NIU": 17499892, "NIS_RAD_1": 3800284, "NIC": 3800284.0, "MEDIDOR": "2022121612", "DIRECCION_CLIENTE": "CL 1  No. CR 2 -  1", "NOMBRE_CLIENTE": "MARCO AURELIO DE LA HOZ MEDINA"}, {"MATRÍCULA CT": "A070578", "NIU": 19590189, "NIS_RAD_1": 8438578, "NIC": 7039267.0, "MEDIDOR": "2022050788", "DIRECCION_CLIENTE": "CL 1  No. CR 2 -  160", "NOMBRE_CLIENTE": "JHONATAN VASCO HINCAPIE"}, {"MATRÍCULA CT": "A070578", "NIU": 18263526, "NIS_RAD_1": 6241984, "NIC": 6223337.0, "MEDIDOR": "11389974-MC941", "DIRECCION_CLIENTE": "CL 1  No. CR 2 -  139", "NOMBRE_CLIENTE": "ORFELI QUINTERO"}, {"MATRÍCULA CT": "A070578", "NIU": 18330938, "NIS_RAD_1": 6586741, "NIC": 6532073.0, "MEDIDOR": "2022012395", "DIRECCION_CLIENTE": "CL 1  No. 3 -  101", "NOMBRE_CLIENTE": "DENIS MARIA SILVA"}, {"MATRÍCULA CT": "A070578", "NIU": 18212030, "NIS_RAD_1": 3800288, "NIC": 3800288.0, "MEDIDOR": "3925526-MC079", "DIRECCION_CLIENTE": "CL 1  No. CR 2 -  102", "NOMBRE_CLIENTE": "MIGUEL TORRES"}, {"MATRÍCULA CT": "A070578", "NIU": 20048313, "NIS_RAD_1": 1882465, "NIC": 7264819.0, "MEDIDOR": "12173197-MCA54", "DIRECCION_CLIENTE": "CL 1  No. CR 2 -  162", "NOMBRE_CLIENTE": "JOSE JAVIER PRADO ROMERO"}, {"MATRÍCULA CT": "A070578", "NIU": 18944581, "NIS_RAD_1": 8112730, "NIC": 6940234.0, "MEDIDOR": "0175620-MC942", "DIRECCION_CLIENTE": "CL 1  No. CR 2 -  145", "NOMBRE_CLIENTE": "JORGE PADIERMA"}, {"MATRÍCULA CT": "A070578", "NIU": 19764153, "NIS_RAD_1": 3212875, "NIC": 7109960.0, "MEDIDOR": "0000565414-MC957", "DIRECCION_CLIENTE": "CL 1  No. CR 2 -  171", "NOMBRE_CLIENTE": "ELSA INES RUIZ LEON"}, {"MATRÍCULA CT": "A070578", "NIU": 18937509, "NIS_RAD_1": 8112713, "NIC": 6940230.0, "MEDIDOR": "0175542-MC942", "DIRECCION_CLIENTE": "CL 1  No. CR 2 -  145", "NOMBRE_CLIENTE": "JORGE PADIERMA"}, {"MATRÍCULA CT": "A070578", "NIU": 19590176, "NIS_RAD_1": 8438574, "NIC": 7039265.0, "MEDIDOR": "2022050794", "DIRECCION_CLIENTE": "CL 1  No. CR 2 -  154", "NOMBRE_CLIENTE": "OBERT ESTRADA"}, {"MATRÍCULA CT": "A070578", "NIU": 18979711, "NIS_RAD_1": 8143850, "NIC": 6947876.0, "MEDIDOR": "2022050787", "DIRECCION_CLIENTE": "CL 1  No. CR 2 -  103", "NOMBRE_CLIENTE": "CHARLIS MOYA HINCAPIE"}, {"MATRÍCULA CT": "A070578", "NIU": 17499895, "NIS_RAD_1": 3800287, "NIC": 3800287.0, "MEDIDOR": "4539098-MC879", "DIRECCION_CLIENTE": "CL 1  No. CR 2 -  103", "NOMBRE_CLIENTE": "EDELMIRA HINCAPIE"}, {"MATRÍCULA CT": "A070578", "NIU": 18356342, "NIS_RAD_1": 6822790, "NIC": 6597418.0, "MEDIDOR": "2022051024", "DIRECCION_CLIENTE": "CL 1  No. CR 2 -  103", "NOMBRE_CLIENTE": "YENNY JOHANA BOHORQUEZ"}, {"MATRÍCULA CT": "A070578", "NIU": 18303096, "NIS_RAD_1": 6308891, "NIC": 6253783.0, "MEDIDOR": "4593786-MC879", "DIRECCION_CLIENTE": "CL 1  No. CR 2 -  146", "NOMBRE_CLIENTE": "JAIRO GUTIERREZ"}, {"MATRÍCULA CT": "A070578", "NIU": 18318023, "NIS_RAD_1": 6612316, "NIC": 6542159.0, "MEDIDOR": "167412-MC989", "DIRECCION_CLIENTE": "CL 1  No. CR 2 -  130", "NOMBRE_CLIENTE": "JOSE ALZATE"}, {"MATRÍCULA CT": "A070578", "NIU": 18263525, "NIS_RAD_1": 6241982, "NIC": 6223336.0, "MEDIDOR": "4162286-MC879", "DIRECCION_CLIENTE": "CL 1  No. CR 2 -  145", "NOMBRE_CLIENTE": "JORGE PADIERNA"}, {"MATRÍCULA CT": "A070578", "NIU": 18263527, "NIS_RAD_1": 6241986, "NIC": 6223338.0, "MEDIDOR": "4162096-MC879", "DIRECCION_CLIENTE": "CL 1  No. CR 2 -  138", "NOMBRE_CLIENTE": "BEATRIZ ELENA FLOREZ"}, {"MATRÍCULA CT": "A070578", "NIU": 18251394, "NIS_RAD_1": 6234454, "NIC": 6219572.0, "MEDIDOR": "11365643-MC941", "DIRECCION_CLIENTE": "CL 1  No. CR 2 -  144", "NOMBRE_CLIENTE": "MARLENE MARIN CARDONA"}], "TOTAL_CLIENTES": 40}