{"CODIGO_TRANSFORMADOR": "65791382", "MATRÍCULA CT": "X000475", "MATRÍCULA_TRANSFORMADOR": "C00364", "MATRÍCULA_CENSO": "C00364", "DIRECCIÓN TRAFO": "CL 85 NO 78D - 26 EDIFICIO PUERTO REAL", "POTENCIA_NOMINAL": "630.0", "LEVANTAR_STATUS": "NO LEVANTAR", "LATITUD": "11.0247143", "LONGITUD": "-74.8050178", "CLIENTES": [{"MATRÍCULA CT": "X000475", "NIU": 21441445, "NIS_RAD_1": 486384, "NIC": 1354040.0, "MEDIDOR": "1069679-MCA47", "DIRECCION_CLIENTE": "CL 85  No. CR 78D -  26", "NOMBRE_CLIENTE": "ANA MILENA RODRIGUEZ CASTILLO"}, {"MATRÍCULA CT": "X000475", "NIU": 21441543, "NIS_RAD_1": 486500, "NIC": 1354147.0, "MEDIDOR": "1069584-MCA47", "DIRECCION_CLIENTE": "CL 85  No. CR 78D -  26", "NOMBRE_CLIENTE": "ERIKA NATALIA VASQUEZ LEON"}, {"MATRÍCULA CT": "X000475", "NIU": 21442155, "NIS_RAD_1": 487861, "NIC": 1354247.0, "MEDIDOR": "1069705-MCA47", "DIRECCION_CLIENTE": "CL 85  No. CR 78D -  26", "NOMBRE_CLIENTE": "JULIO CESAR YI AGUIRRE"}, {"MATRÍCULA CT": "X000475", "NIU": 21441511, "NIS_RAD_1": 486457, "NIC": 1354136.0, "MEDIDOR": "1069738-MCA47", "DIRECCION_CLIENTE": "CL 85  No. CR 78D -  26", "NOMBRE_CLIENTE": "JUAN CAMILO DIAZ ARIEL"}, {"MATRÍCULA CT": "X000475", "NIU": 21441429, "NIS_RAD_1": 486365, "NIC": "", "MEDIDOR": "", "DIRECCION_CLIENTE": "CL 85  No. CR 78D -  26", "NOMBRE_CLIENTE": "ELKIN MOISES PIMIENTA TORRES"}, {"MATRÍCULA CT": "X000475", "NIU": 21441429, "NIS_RAD_1": 486365, "NIC": "", "MEDIDOR": "1069631-MCA47", "DIRECCION_CLIENTE": "CL 85  No. CR 78D -  26", "NOMBRE_CLIENTE": "ISSA SAIEH & CIA LTDA"}, {"MATRÍCULA CT": "X000475", "NIU": 21441439, "NIS_RAD_1": 486378, "NIC": 1354038.0, "MEDIDOR": "1069751-MCA48", "DIRECCION_CLIENTE": "CL 85  No. CR 78D -  26", "NOMBRE_CLIENTE": "Sin definir PARAISO 85 SAS"}, {"MATRÍCULA CT": "X000475", "NIU": 21441444, "NIS_RAD_1": 486383, "NIC": 1354218.0, "MEDIDOR": "1069736-MCA47", "DIRECCION_CLIENTE": "CL 85  No. CR 78D -  26", "NOMBRE_CLIENTE": "ROSAURA RIZZO MADRID"}, {"MATRÍCULA CT": "X000475", "NIU": 21441446, "NIS_RAD_1": 486385, "NIC": 1354220.0, "MEDIDOR": "1069706-MCA47", "DIRECCION_CLIENTE": "CL 85  No. CR 78D -  26", "NOMBRE_CLIENTE": "MIREYA VEGA"}, {"MATRÍCULA CT": "X000475", "NIU": 21441447, "NIS_RAD_1": 486386, "NIC": 1354041.0, "MEDIDOR": "1069697-MCA47", "DIRECCION_CLIENTE": "CL 85  No. CR 78D -  26", "NOMBRE_CLIENTE": "CIRO ALFONSO GOMEZ RUEDA"}, {"MATRÍCULA CT": "X000475", "NIU": 21441449, "NIS_RAD_1": 486388, "NIC": 1354223.0, "MEDIDOR": "1069634-MCA47", "DIRECCION_CLIENTE": "CL 85  No. CR 78D -  26", "NOMBRE_CLIENTE": "JORGE ENRIQUE ARAUJO LARIOS"}, {"MATRÍCULA CT": "X000475", "NIU": 21441452, "NIS_RAD_1": 486394, "NIC": 1354225.0, "MEDIDOR": "1069635-MCA47", "DIRECCION_CLIENTE": "CL 85  No. CR 78D -  26", "NOMBRE_CLIENTE": "EMILIA NANCY BERDUGO DE LLANAO GUSTAVO JOSE LLANOS"}, {"MATRÍCULA CT": "X000475", "NIU": 21441454, "NIS_RAD_1": 486396, "NIC": 1354227.0, "MEDIDOR": "1069636-MCA47", "DIRECCION_CLIENTE": "CL 85  No. CR 78D -  26", "NOMBRE_CLIENTE": "YEISON JESURUN CERME"}, {"MATRÍCULA CT": "X000475", "NIU": 21441455, "NIS_RAD_1": 486397, "NIC": 1354046.0, "MEDIDOR": "1069672-MCA47", "DIRECCION_CLIENTE": "CL 85  No. CR 78D -  26", "NOMBRE_CLIENTE": "Sin definir PARAISO 85 SAS"}, {"MATRÍCULA CT": "X000475", "NIU": 21441460, "NIS_RAD_1": 486402, "NIC": 1354048.0, "MEDIDOR": "1069698-MCA47", "DIRECCION_CLIENTE": "CL 85  No. CR 78D -  26", "NOMBRE_CLIENTE": "YESIT GUZMAN"}, {"MATRÍCULA CT": "X000475", "NIU": 21441461, "NIS_RAD_1": 486403, "NIC": 1354233.0, "MEDIDOR": "1069575-MCA47", "DIRECCION_CLIENTE": "CL 85  No. CR 78D -  26", "NOMBRE_CLIENTE": "NELSON ENRIQUE GARCIA PEREZ"}, {"MATRÍCULA CT": "X000475", "NIU": 21441463, "NIS_RAD_1": 486405, "NIC": 1354049.0, "MEDIDOR": "1069670-MCA47", "DIRECCION_CLIENTE": "CL 85  No. CR 78D -  26", "NOMBRE_CLIENTE": "Sin definir PARAISO 85 SAS"}, {"MATRÍCULA CT": "X000475", "NIU": 21441470, "NIS_RAD_1": 486416, "NIC": 1354242.0, "MEDIDOR": "1069699-MCA47", "DIRECCION_CLIENTE": "CL 85  No. CR 78D -  26", "NOMBRE_CLIENTE": "KARINA MUOZ GOMEZ GONZALO IVAN ALZATE"}, {"MATRÍCULA CT": "X000475", "NIU": 21441471, "NIS_RAD_1": 486417, "NIC": 1354053.0, "MEDIDOR": "1069653-MCA47", "DIRECCION_CLIENTE": "CL 85  No. CR 78D -  26", "NOMBRE_CLIENTE": "JAIRO JASSIT MANZUR CARO"}, {"MATRÍCULA CT": "X000475", "NIU": 21441473, "NIS_RAD_1": 486419, "NIC": 1354052.0, "MEDIDOR": "1069692-MCA47", "DIRECCION_CLIENTE": "CL 85  No. CR 78D -  26", "NOMBRE_CLIENTE": "ANA CECILIA CARO CHAVEZ"}, {"MATRÍCULA CT": "X000475", "NIU": 21441479, "NIS_RAD_1": 486425, "NIC": 1354055.0, "MEDIDOR": "1069689-MCA47", "DIRECCION_CLIENTE": "CL 85  No. CR 78D -  26", "NOMBRE_CLIENTE": "INGRID PAOLA DIAZ CARDENAS"}, {"MATRÍCULA CT": "X000475", "NIU": 21441481, "NIS_RAD_1": 486427, "NIC": 1354243.0, "MEDIDOR": "1069638-MCA47", "DIRECCION_CLIENTE": "CL 85  No. CR 78D -  26", "NOMBRE_CLIENTE": "LISET DEL CARMEN LLANOS BERDUG MARIO DE JESUS ARENA"}, {"MATRÍCULA CT": "X000475", "NIU": 21441483, "NIS_RAD_1": 486429, "NIC": 1354056.0, "MEDIDOR": "1069675-MCA47", "DIRECCION_CLIENTE": "CL 85  No. CR 78D -  26", "NOMBRE_CLIENTE": "OSCAR ANTONIO ORTIZ AFRICANO"}, {"MATRÍCULA CT": "X000475", "NIU": 21441484, "NIS_RAD_1": 486430, "NIC": 1354244.0, "MEDIDOR": "1069573-MCA47", "DIRECCION_CLIENTE": "CL 85  No. CR 78D -  26", "NOMBRE_CLIENTE": "DINA ESTHER PEREZ TAPIA AGUSTIN JOSE SANCHEZ"}, {"MATRÍCULA CT": "X000475", "NIU": 21441489, "NIS_RAD_1": 486435, "NIC": 1354057.0, "MEDIDOR": "1069683-MCA47", "DIRECCION_CLIENTE": "CL 85  No. CR 78D -  26", "NOMBRE_CLIENTE": "Sin definir PARAISO 85 SAS"}, {"MATRÍCULA CT": "X000475", "NIU": 21441491, "NIS_RAD_1": 486437, "NIC": 1354059.0, "MEDIDOR": "1069758-MCA47", "DIRECCION_CLIENTE": "CL 85  No. CR 78D -  26", "NOMBRE_CLIENTE": "LUZ MARINA SANTOS BOVEA"}, {"MATRÍCULA CT": "X000475", "NIU": 21441492, "NIS_RAD_1": 486438, "NIC": 1354026.0, "MEDIDOR": "1069729-MCA47", "DIRECCION_CLIENTE": "CL 85  No. CR 78D -  26", "NOMBRE_CLIENTE": "SONIA ANGELICA GONZALEZ CARDENAS"}, {"MATRÍCULA CT": "X000475", "NIU": 21441499, "NIS_RAD_1": 486445, "NIC": 1354064.0, "MEDIDOR": "1069691-MCA47", "DIRECCION_CLIENTE": "CL 85  No. CR 78D -  26", "NOMBRE_CLIENTE": "ALFONSO MONTAO"}, {"MATRÍCULA CT": "X000475", "NIU": 21441505, "NIS_RAD_1": 486451, "NIC": 1354130.0, "MEDIDOR": "1069611-MCA47", "DIRECCION_CLIENTE": "CL 85  No. CR 78D -  26", "NOMBRE_CLIENTE": "JUAN CARLOS ASHTON CABRERA"}, {"MATRÍCULA CT": "X000475", "NIU": 21441506, "NIS_RAD_1": 486452, "NIC": 1354066.0, "MEDIDOR": "1069686-MCA47", "DIRECCION_CLIENTE": "CL 85  No. CR 78D -  26", "NOMBRE_CLIENTE": "DAIRO ENRIQUE MUOZ EBRATT"}, {"MATRÍCULA CT": "X000475", "NIU": 21441508, "NIS_RAD_1": 486454, "NIC": 1354069.0, "MEDIDOR": "1069680-MCA47", "DIRECCION_CLIENTE": "CL 85  No. CR 78D -  26", "NOMBRE_CLIENTE": "EVER GUTIERREZ"}, {"MATRÍCULA CT": "X000475", "NIU": 21441510, "NIS_RAD_1": 486456, "NIC": 1354070.0, "MEDIDOR": "1069674-MCA47", "DIRECCION_CLIENTE": "CL 85  No. CR 78D -  26", "NOMBRE_CLIENTE": "ROSA ALICIA BARRERA LUQUE"}, {"MATRÍCULA CT": "X000475", "NIU": 21441514, "NIS_RAD_1": 486460, "NIC": 1354141.0, "MEDIDOR": "1069707-MCA47", "DIRECCION_CLIENTE": "CL 85  No. CR 78D -  26", "NOMBRE_CLIENTE": "DAVID RAMON ASHTON CABRERA"}, {"MATRÍCULA CT": "X000475", "NIU": 21441516, "NIS_RAD_1": 486462, "NIC": 1354146.0, "MEDIDOR": "1069754-MCA47", "DIRECCION_CLIENTE": "CL 85  No. CR 78D -  26", "NOMBRE_CLIENTE": "ELVIMAR MARIA HERNANDEZ CORREO"}, {"MATRÍCULA CT": "X000475", "NIU": 21441520, "NIS_RAD_1": 486467, "NIC": 1354082.0, "MEDIDOR": "1221212397-MCA39", "DIRECCION_CLIENTE": "CL 85  No. CR 78D -  26", "NOMBRE_CLIENTE": "VICENTE LUIS NICOLELLA CABALLERON"}, {"MATRÍCULA CT": "X000475", "NIU": 21441521, "NIS_RAD_1": 486468, "NIC": 1354097.0, "MEDIDOR": "1221211842-MCA39", "DIRECCION_CLIENTE": "CL 85  No. CR 78D -  26", "NOMBRE_CLIENTE": "DALIS ELVIRA PADILLA ROBALLO"}, {"MATRÍCULA CT": "X000475", "NIU": 21441522, "NIS_RAD_1": 486469, "NIC": 1354099.0, "MEDIDOR": "1069681-MCA47", "DIRECCION_CLIENTE": "CL 85  No. CR 78D -  26", "NOMBRE_CLIENTE": "HUMBERTO RUIZ CARPIO"}, {"MATRÍCULA CT": "X000475", "NIU": 21441525, "NIS_RAD_1": 486474, "NIC": 1354110.0, "MEDIDOR": "1069687-MCA47", "DIRECCION_CLIENTE": "CL 85  No. CR 78D -  26", "NOMBRE_CLIENTE": "FRANKLIN FONTALVO"}, {"MATRÍCULA CT": "X000475", "NIU": 21441530, "NIS_RAD_1": 486485, "NIC": 1354126.0, "MEDIDOR": "1069588-MCA47", "DIRECCION_CLIENTE": "CL 85  No. CR 78D -  26", "NOMBRE_CLIENTE": "ALEXIS ALFONSO RODRIGUEZ CANCINO"}, {"MATRÍCULA CT": "X000475", "NIU": 21441533, "NIS_RAD_1": 486488, "NIC": 1354129.0, "MEDIDOR": "1069659-MCA47", "DIRECCION_CLIENTE": "CL 85  No. CR 78D -  26", "NOMBRE_CLIENTE": "KAREN ESTHER DE LA CRUZ VILORIA"}, {"MATRÍCULA CT": "X000475", "NIU": 21441534, "NIS_RAD_1": 486489, "NIC": 1354135.0, "MEDIDOR": "1069660-MCA47", "DIRECCION_CLIENTE": "CL 85  No. CR 78D -  26", "NOMBRE_CLIENTE": "Jean Carlos Barrios Lanao"}, {"MATRÍCULA CT": "X000475", "NIU": 21441538, "NIS_RAD_1": 486495, "NIC": 1354145.0, "MEDIDOR": "1069618-MCA47", "DIRECCION_CLIENTE": "CL 85  No. CR 78D -  26", "NOMBRE_CLIENTE": "RAMON BUELVAS OLMOS"}, {"MATRÍCULA CT": "X000475", "NIU": 21441542, "NIS_RAD_1": 486499, "NIC": 1354154.0, "MEDIDOR": "1069612-MCA47", "DIRECCION_CLIENTE": "CL 85  No. CR 78D -  26", "NOMBRE_CLIENTE": "OSCAR OCTAVIO DONADO JIMENZ"}, {"MATRÍCULA CT": "X000475", "NIU": 21441546, "NIS_RAD_1": 486503, "NIC": 1354161.0, "MEDIDOR": "1069651-MCA47", "DIRECCION_CLIENTE": "CL 85  No. CR 78D -  26", "NOMBRE_CLIENTE": "PATRICIA ELENA ROMERO SANCHEZ"}, {"MATRÍCULA CT": "X000475", "NIU": 21441548, "NIS_RAD_1": 486507, "NIC": 1354169.0, "MEDIDOR": "1069730-MCA47", "DIRECCION_CLIENTE": "CL 85  No. CR 78D -  26", "NOMBRE_CLIENTE": "HANS MARTINEZ DE LEO"}, {"MATRÍCULA CT": "X000475", "NIU": 21441555, "NIS_RAD_1": 486520, "NIC": 1354158.0, "MEDIDOR": "1069656-MCA47", "DIRECCION_CLIENTE": "CL 85  No. CR 78D -  26", "NOMBRE_CLIENTE": "Sin definir PARAISO 85 SAS"}, {"MATRÍCULA CT": "X000475", "NIU": 21441558, "NIS_RAD_1": 486523, "NIC": 1354153.0, "MEDIDOR": "1069654-MCA47", "DIRECCION_CLIENTE": "CL 85  No. CR 78D -  26", "NOMBRE_CLIENTE": "Sin definir LIRIS PAOLA QUINTERO"}, {"MATRÍCULA CT": "X000475", "NIU": 21441559, "NIS_RAD_1": 486526, "NIC": 1354144.0, "MEDIDOR": "1069657-MCA47", "DIRECCION_CLIENTE": "CL 85  No. CR 78D -  26", "NOMBRE_CLIENTE": "Sin definir CRISTIAN GRISALEZ"}, {"MATRÍCULA CT": "X000475", "NIU": 21441405, "NIS_RAD_1": 486337, "NIC": 1354166.0, "MEDIDOR": "1069664-MCA47", "DIRECCION_CLIENTE": "CL 85  No. CR 78D -  26", "NOMBRE_CLIENTE": "ALEJANDRO CARREO VASQUEZ"}, {"MATRÍCULA CT": "X000475", "NIU": 21441406, "NIS_RAD_1": 486338, "NIC": 1354179.0, "MEDIDOR": "1069666-MCA47", "DIRECCION_CLIENTE": "CL 85  No. CR 78D -  26", "NOMBRE_CLIENTE": "VLADIMIR ANGARITA QUINTERO"}, {"MATRÍCULA CT": "X000475", "NIU": 21441408, "NIS_RAD_1": 486340, "NIC": 1354181.0, "MEDIDOR": "1069581-MCA47", "DIRECCION_CLIENTE": "CL 85  No. CR 78D -  26", "NOMBRE_CLIENTE": "MAURICIO ALBERTO GONZALEZ RODRIGUEZ"}, {"MATRÍCULA CT": "X000475", "NIU": 21441409, "NIS_RAD_1": 486341, "NIC": 1354182.0, "MEDIDOR": "1069580-MCA47", "DIRECCION_CLIENTE": "CL 85  No. CR 78D -  26", "NOMBRE_CLIENTE": "LILIANA MARGARITA VISBAL GUTIERREZ"}, {"MATRÍCULA CT": "X000475", "NIU": 21441411, "NIS_RAD_1": 486345, "NIC": 1354183.0, "MEDIDOR": "1069579-MCA47", "DIRECCION_CLIENTE": "CL 85  No. CR 78D -  26", "NOMBRE_CLIENTE": "LUZ GLADYS GARCIA MAESTRE"}, {"MATRÍCULA CT": "X000475", "NIU": 21441414, "NIS_RAD_1": 486348, "NIC": 1354189.0, "MEDIDOR": "1069667-MCA47", "DIRECCION_CLIENTE": "CL 85  No. CR 78D -  26", "NOMBRE_CLIENTE": "DIANA MARCELA BARRIOS"}, {"MATRÍCULA CT": "X000475", "NIU": 21441418, "NIS_RAD_1": 486352, "NIC": 1354194.0, "MEDIDOR": "1069629-MCA47", "DIRECCION_CLIENTE": "CL 85  No. CR 78D -  26", "NOMBRE_CLIENTE": "SILVIA PATRICIO"}, {"MATRÍCULA CT": "X000475", "NIU": 21441419, "NIS_RAD_1": 486353, "NIC": 1354198.0, "MEDIDOR": "1069577-MCA47", "DIRECCION_CLIENTE": "CL 85  No. CR 78D -  26", "NOMBRE_CLIENTE": "SADITH ENRIQUE ORTIZ RODRIGUEZ"}, {"MATRÍCULA CT": "X000475", "NIU": 21441433, "NIS_RAD_1": 486369, "NIC": 1354033.0, "MEDIDOR": "1069750-MCA47", "DIRECCION_CLIENTE": "CL 85  No. CR 78D -  26", "NOMBRE_CLIENTE": "HANSEL DAYAN GONZALES ROMERO"}, {"MATRÍCULA CT": "X000475", "NIU": 21441458, "NIS_RAD_1": 486400, "NIC": 1354047.0, "MEDIDOR": "1069673-MCA47", "DIRECCION_CLIENTE": "CL 85  No. CR 78D -  26", "NOMBRE_CLIENTE": "JAVIER DE JESUS ALVARES GUTIERREZ"}, {"MATRÍCULA CT": "X000475", "NIU": 21441495, "NIS_RAD_1": 486441, "NIC": 1354061.0, "MEDIDOR": "1069609-MCA47", "DIRECCION_CLIENTE": "CL 85  No. CR 78D -  26", "NOMBRE_CLIENTE": "MILAGROS SOLEDAD GONZALEZ GARRIDO"}, {"MATRÍCULA CT": "X000475", "NIU": 21441524, "NIS_RAD_1": 486471, "NIC": 1354107.0, "MEDIDOR": "1069684-MCA47", "DIRECCION_CLIENTE": "CL 85  No. CR 78D -  26", "NOMBRE_CLIENTE": "MANUEL JOSE CARDONA HERNANDEZ"}, {"MATRÍCULA CT": "X000475", "NIU": 21441526, "NIS_RAD_1": 486477, "NIC": 1354117.0, "MEDIDOR": "1069682-MCA47", "DIRECCION_CLIENTE": "CL 85  No. CR 78D -  26", "NOMBRE_CLIENTE": "YULLY JOHANNA MERCADO NAVARRO"}, {"MATRÍCULA CT": "X000475", "NIU": 21441404, "NIS_RAD_1": 486334, "NIC": 1354164.0, "MEDIDOR": "1069663-MCA47", "DIRECCION_CLIENTE": "CL 85  No. CR 78D -  26", "NOMBRE_CLIENTE": "SOL MARILYS PEREZ TORRES"}, {"MATRÍCULA CT": "X000475", "NIU": 21441547, "NIS_RAD_1": 486506, "NIC": 1354165.0, "MEDIDOR": "1069582-MCA47", "DIRECCION_CLIENTE": "CL 85  No. CR 78D -  26", "NOMBRE_CLIENTE": "NUGUET CURE NUGUET CURE"}, {"MATRÍCULA CT": "X000475", "NIU": 21442145, "NIS_RAD_1": 487845, "NIC": "", "MEDIDOR": "", "DIRECCION_CLIENTE": "CL 85  No. CR 78D -  26", "NOMBRE_CLIENTE": ""}, {"MATRÍCULA CT": "X000475", "NIU": 21441430, "NIS_RAD_1": 486366, "NIC": 1354031.0, "MEDIDOR": "1069696-MCA47", "DIRECCION_CLIENTE": "CL 85  No. CR 78D -  26", "NOMBRE_CLIENTE": "Sin definir PARAISO 85 SAS"}, {"MATRÍCULA CT": "X000475", "NIU": 21441549, "NIS_RAD_1": 486508, "NIC": 1354180.0, "MEDIDOR": "1069701-MCA47", "DIRECCION_CLIENTE": "CL 85  No. CR 78D -  26", "NOMBRE_CLIENTE": "Sin definir PARAISO 85 SAS"}, {"MATRÍCULA CT": "X000475", "NIU": 21442152, "NIS_RAD_1": 487856, "NIC": "", "MEDIDOR": "", "DIRECCION_CLIENTE": "CL 85  No. CR 78D -  26", "NOMBRE_CLIENTE": ""}, {"MATRÍCULA CT": "X000475", "NIU": 21367478, "NIS_RAD_1": 3799805, "NIC": 7987444.0, "MEDIDOR": "054151506-MC975", "DIRECCION_CLIENTE": "CL 85  No. CR 78D -  26", "NOMBRE_CLIENTE": "EDIFICIO PUERTO REAL PH "}, {"MATRÍCULA CT": "X000475", "NIU": 21441498, "NIS_RAD_1": 486444, "NIC": 1354063.0, "MEDIDOR": "1069693-MCA47", "DIRECCION_CLIENTE": "CL 85  No. CR 78D -  26", "NOMBRE_CLIENTE": "LEIDY DAYANA SOTO ABRIL"}, {"MATRÍCULA CT": "X000475", "NIU": 21441443, "NIS_RAD_1": 486382, "NIC": 1354039.0, "MEDIDOR": "1069688-MCA47", "DIRECCION_CLIENTE": "CL 85  No. CR 78D -  26", "NOMBRE_CLIENTE": "DIANA MARTINEZ"}, {"MATRÍCULA CT": "X000475", "NIU": 21441536, "NIS_RAD_1": 486491, "NIC": 1354137.0, "MEDIDOR": "1069661-MCA47", "DIRECCION_CLIENTE": "CL 85  No. CR 78D -  26", "NOMBRE_CLIENTE": "KARIM ROBERT CACHELEZ"}, {"MATRÍCULA CT": "X000475", "NIU": 21441497, "NIS_RAD_1": 486443, "NIC": 1354118.0, "MEDIDOR": "1069700-MCA47", "DIRECCION_CLIENTE": "CL 85  No. CR 78D -  26", "NOMBRE_CLIENTE": "MARIA JOSE CASTAEDA SUAREZ"}, {"MATRÍCULA CT": "X000475", "NIU": 21441413, "NIS_RAD_1": 486347, "NIC": 1354011.0, "MEDIDOR": "1069757-MCA47", "DIRECCION_CLIENTE": "CL 85  No. CR 78D -  26", "NOMBRE_CLIENTE": "RICARDO SANDOVAL CHEGWIN"}, {"MATRÍCULA CT": "X000475", "NIU": 21441426, "NIS_RAD_1": 486360, "NIC": 1354020.0, "MEDIDOR": "1069671-MCA47", "DIRECCION_CLIENTE": "CL 85  No. CR 78D -  26", "NOMBRE_CLIENTE": "ROSARY DEL CARMEN DONADO"}, {"MATRÍCULA CT": "X000475", "NIU": 21441561, "NIS_RAD_1": 486530, "NIC": 1354138.0, "MEDIDOR": "1069702-MCA47", "DIRECCION_CLIENTE": "CL 85  No. CR 78D -  26", "NOMBRE_CLIENTE": "JUAN CARLOS PULIDO RODRIGUEZ"}, {"MATRÍCULA CT": "X000475", "NIU": 21442149, "NIS_RAD_1": 487851, "NIC": "", "MEDIDOR": "", "DIRECCION_CLIENTE": "CL 85  No. CR 78D -  26", "NOMBRE_CLIENTE": ""}, {"MATRÍCULA CT": "X000475", "NIU": 21441557, "NIS_RAD_1": 486522, "NIC": 1354155.0, "MEDIDOR": "1069617-MCA47", "DIRECCION_CLIENTE": "CL 85  No. CR 78D -  26", "NOMBRE_CLIENTE": "Sin definir PARAISO 85 SAS"}, {"MATRÍCULA CT": "X000475", "NIU": 21441450, "NIS_RAD_1": 486391, "NIC": 1354043.0, "MEDIDOR": "1069749-MCA47", "DIRECCION_CLIENTE": "CL 85  No. CR 78D -  26", "NOMBRE_CLIENTE": "JULIA ROSA POLO TEJEDA"}, {"MATRÍCULA CT": "X000475", "NIU": 21441466, "NIS_RAD_1": 486408, "NIC": 1354050.0, "MEDIDOR": "1069677-MCA47", "DIRECCION_CLIENTE": "CL 85  No. CR 78D -  26", "NOMBRE_CLIENTE": "YADIRA LUZ BARRIOS PERTUZ"}, {"MATRÍCULA CT": "X000475", "NIU": 21441437, "NIS_RAD_1": 486376, "NIC": 1354037.0, "MEDIDOR": "1069685-MCA47", "DIRECCION_CLIENTE": "CL 85  No. CR 78D -  26", "NOMBRE_CLIENTE": "MARLON CERVANTES CERVANTES"}, {"MATRÍCULA CT": "X000475", "NIU": 21441485, "NIS_RAD_1": 486431, "NIC": 1354249.0, "MEDIDOR": "1069570-MCA47", "DIRECCION_CLIENTE": "CL 85  No. CR 78D -  26", "NOMBRE_CLIENTE": "TATIANA MARCELLA GUTIERREZ ROMERO"}, {"MATRÍCULA CT": "X000475", "NIU": 21441545, "NIS_RAD_1": 486502, "NIC": 1354157.0, "MEDIDOR": "1069652-MCA47", "DIRECCION_CLIENTE": "CL 85  No. CR 78D -  26", "NOMBRE_CLIENTE": "CHRISTIAN ELIECER GONZALEZ MIRANDA"}, {"MATRÍCULA CT": "X000475", "NIU": 21441553, "NIS_RAD_1": 486514, "NIC": 1354162.0, "MEDIDOR": "1069616-MCA47", "DIRECCION_CLIENTE": "CL 85  No. CR 78D -  26", "NOMBRE_CLIENTE": "Sin definir ADRIANA BEATRIZ BETA"}, {"MATRÍCULA CT": "X000475", "NIU": 21441432, "NIS_RAD_1": 486368, "NIC": 1354212.0, "MEDIDOR": "1069632-MCA47", "DIRECCION_CLIENTE": "CL 85  No. CR 78D -  26", "NOMBRE_CLIENTE": "BERMA RONCALLO BARCENAS"}, {"MATRÍCULA CT": "X000475", "NIU": 21441503, "NIS_RAD_1": 486449, "NIC": 1354127.0, "MEDIDOR": "1069610-MCA47", "DIRECCION_CLIENTE": "CL 85  No. CR 78D -  26", "NOMBRE_CLIENTE": "JAZMIN DE LOS MILAGROS MORALEZ GUILLERMO JOSE ALMAR"}, {"MATRÍCULA CT": "X000475", "NIU": 21441476, "NIS_RAD_1": 486422, "NIC": 1354252.0, "MEDIDOR": "1069694-MCA47", "DIRECCION_CLIENTE": "CL 85  No. CR 78D -  26", "NOMBRE_CLIENTE": "INGRID PAOLA DIAZ CARDENAS"}, {"MATRÍCULA CT": "X000475", "NIU": 21442151, "NIS_RAD_1": 487855, "NIC": "", "MEDIDOR": "", "DIRECCION_CLIENTE": "CL 85  No. CR 78D -  26", "NOMBRE_CLIENTE": ""}, {"MATRÍCULA CT": "X000475", "NIU": 21441424, "NIS_RAD_1": 486358, "NIC": 1354254.0, "MEDIDOR": "1069732-MCA47", "DIRECCION_CLIENTE": "CL 85  No. CR 78D -  26", "NOMBRE_CLIENTE": "DANIEL ALEXANDER MERCADO RODRIGUEZ"}, {"MATRÍCULA CT": "X000475", "NIU": 21441435, "NIS_RAD_1": 486371, "NIC": 1354036.0, "MEDIDOR": "1069649-MCA47", "DIRECCION_CLIENTE": "CL 85  No. CR 78D -  26", "NOMBRE_CLIENTE": "HOSMAN ENRQUE PEREZ FONSECA"}, {"MATRÍCULA CT": "X000475", "NIU": 21441529, "NIS_RAD_1": 486484, "NIC": 1354122.0, "MEDIDOR": "1221211844-MCA39", "DIRECCION_CLIENTE": "CL 85  No. CR 78D -  26", "NOMBRE_CLIENTE": "LEONARDO ANDRES BARRAZA SUAREZ"}, {"MATRÍCULA CT": "X000475", "NIU": 21441412, "NIS_RAD_1": 486346, "NIC": 1354185.0, "MEDIDOR": "1069578-MCA47", "DIRECCION_CLIENTE": "CL 85  No. CR 78D -  26", "NOMBRE_CLIENTE": "NELSON ARDILA VEGA"}, {"MATRÍCULA CT": "X000475", "NIU": 21441515, "NIS_RAD_1": 486461, "NIC": 1354074.0, "MEDIDOR": "1069658-MCA47", "DIRECCION_CLIENTE": "CL 85  No. CR 78D -  26", "NOMBRE_CLIENTE": "ROBERTO JOSE GOENAGA DE LA ASUNCION"}, {"MATRÍCULA CT": "X000475", "NIU": 21441541, "NIS_RAD_1": 486498, "NIC": 1354143.0, "MEDIDOR": "1069585-MCA47", "DIRECCION_CLIENTE": "CL 85  No. CR 78D -  26", "NOMBRE_CLIENTE": "YAZMIN DEL CARMEN RHENALS GALVIS"}, {"MATRÍCULA CT": "X000475", "NIU": 21442148, "NIS_RAD_1": 487850, "NIC": "", "MEDIDOR": "", "DIRECCION_CLIENTE": "CL 85  No. CR 78D -  26", "NOMBRE_CLIENTE": ""}, {"MATRÍCULA CT": "X000475", "NIU": 21441502, "NIS_RAD_1": 486448, "NIC": 1354124.0, "MEDIDOR": "1069613-MCA47", "DIRECCION_CLIENTE": "CL 85  No. CR 78D -  26", "NOMBRE_CLIENTE": "ROSIRIS DIAZ XXX"}, {"MATRÍCULA CT": "X000475", "NIU": 21441451, "NIS_RAD_1": 486392, "NIC": 1354044.0, "MEDIDOR": "1069571-MCA47", "DIRECCION_CLIENTE": "CL 85  No. CR 78D -  26", "NOMBRE_CLIENTE": "MARCO ALBERTO CASTILLO BELTRAN"}, {"MATRÍCULA CT": "X000475", "NIU": 21441512, "NIS_RAD_1": 486458, "NIC": 1354071.0, "MEDIDOR": "1069676-MCA47", "DIRECCION_CLIENTE": "CL 85  No. CR 78D -  26", "NOMBRE_CLIENTE": "MAURICIO RESTREPO JIMENEZ"}, {"MATRÍCULA CT": "X000475", "NIU": 21441469, "NIS_RAD_1": 486411, "NIC": 1354051.0, "MEDIDOR": "1069752-MCA47", "DIRECCION_CLIENTE": "CL 85  No. CR 78D -  26", "NOMBRE_CLIENTE": "EVER ENRIQUE NUEZ PULIDO"}, {"MATRÍCULA CT": "X000475", "NIU": 21441416, "NIS_RAD_1": 486350, "NIC": 1354193.0, "MEDIDOR": "1069669-MC936", "DIRECCION_CLIENTE": "CL 85  No. CR 78D -  26", "NOMBRE_CLIENTE": "KEVIN JOSE GOMEZ CAMARGO"}, {"MATRÍCULA CT": "X000475", "NIU": 21441407, "NIS_RAD_1": 486339, "NIC": 1354170.0, "MEDIDOR": "1069665-MCA47", "DIRECCION_CLIENTE": "CL 85  No. CR 78D -  26", "NOMBRE_CLIENTE": "JEANNINE ESTHER BARRAZA HERNANDEZ"}, {"MATRÍCULA CT": "X000475", "NIU": 21441465, "NIS_RAD_1": 486407, "NIC": 1354235.0, "MEDIDOR": "1069733-MCA47", "DIRECCION_CLIENTE": "CL 85  No. CR 78D -  26", "NOMBRE_CLIENTE": "ALVARO LUIS SANCHEZ MUOZ"}, {"MATRÍCULA CT": "X000475", "NIU": 21441537, "NIS_RAD_1": 486492, "NIC": 1354140.0, "MEDIDOR": "1069662-MCA47", "DIRECCION_CLIENTE": "CL 85  No. CR 78D -  26", "NOMBRE_CLIENTE": "JOHANA ESTHER MENDEZ MARTINEZ"}, {"MATRÍCULA CT": "X000475", "NIU": 21441528, "NIS_RAD_1": 486479, "NIC": 1354121.0, "MEDIDOR": "1069655-MCA47", "DIRECCION_CLIENTE": "CL 85  No. CR 78D -  26", "NOMBRE_CLIENTE": "JOHANA MILETH SARMIENTO"}, {"MATRÍCULA CT": "X000475", "NIU": 21441415, "NIS_RAD_1": 486349, "NIC": 1354253.0, "MEDIDOR": "1069668-MCA47", "DIRECCION_CLIENTE": "CL 85  No. CR 78D -  26", "NOMBRE_CLIENTE": "HILDA MELENDEZ DIAZ"}, {"MATRÍCULA CT": "X000475", "NIU": 21442147, "NIS_RAD_1": 487847, "NIC": "", "MEDIDOR": "", "DIRECCION_CLIENTE": "CL 85  No. CR 78D -  26", "NOMBRE_CLIENTE": ""}, {"MATRÍCULA CT": "X000475", "NIU": 21441453, "NIS_RAD_1": 486395, "NIC": 1354045.0, "MEDIDOR": "1069753-MCA47", "DIRECCION_CLIENTE": "CL 85  No. CR 78D -  26", "NOMBRE_CLIENTE": "MARCO ANTONIO CASTILLO CHARRIS"}, {"MATRÍCULA CT": "X000475", "NIU": 21441509, "NIS_RAD_1": 486455, "NIC": 1354134.0, "MEDIDOR": "1069586-MCA47", "DIRECCION_CLIENTE": "CL 85  No. CR 78D -  26", "NOMBRE_CLIENTE": "JULIAN MARTINEZ VILLALBA"}, {"MATRÍCULA CT": "X000475", "NIU": 21441434, "NIS_RAD_1": 486370, "NIC": 1354213.0, "MEDIDOR": "1069633-MCA47", "DIRECCION_CLIENTE": "CL 85  No. CR 78D -  26", "NOMBRE_CLIENTE": "ANDRES SIERRA HERNANDEZ"}, {"MATRÍCULA CT": "X000475", "NIU": 21441532, "NIS_RAD_1": 486487, "NIC": 1354128.0, "MEDIDOR": "1069587-MCA47", "DIRECCION_CLIENTE": "CL 85  No. CR 78D -  26", "NOMBRE_CLIENTE": "YOLET DELGADO SANCHEZ"}, {"MATRÍCULA CT": "X000475", "NIU": 21441494, "NIS_RAD_1": 486440, "NIC": 1354034.0, "MEDIDOR": "1069737-MCA47", "DIRECCION_CLIENTE": "CL 85  No. CR 78D -  26", "NOMBRE_CLIENTE": "ORLANDO RAFAEL MENDEZ CHAMORRO"}, {"MATRÍCULA CT": "X000475", "NIU": 21441441, "NIS_RAD_1": 486380, "NIC": 1354217.0, "MEDIDOR": "1069734-MCA47", "DIRECCION_CLIENTE": "CL 85  No. CR 78D -  26", "NOMBRE_CLIENTE": "ANDRES FELIPE QUINTERO ARIZA"}, {"MATRÍCULA CT": "X000475", "NIU": 21441425, "NIS_RAD_1": 486359, "NIC": 1354208.0, "MEDIDOR": "1069703-MCA47", "DIRECCION_CLIENTE": "CL 85  No. CR 78D -  26", "NOMBRE_CLIENTE": "ADRIANA PATRICIA OYOLA BOLIVAR"}, {"MATRÍCULA CT": "X000475", "NIU": 21441554, "NIS_RAD_1": 486517, "NIC": 1354159.0, "MEDIDOR": "1069650-MCA47", "DIRECCION_CLIENTE": "CL 85  No. CR 78D -  26", "NOMBRE_CLIENTE": "Sin definir PARAISO 85 SAS"}, {"MATRÍCULA CT": "X000475", "NIU": 21441490, "NIS_RAD_1": 486436, "NIC": 1354022.0, "MEDIDOR": "1221210319-MCA39", "DIRECCION_CLIENTE": "CL 85  No. CR 78D -  26", "NOMBRE_CLIENTE": "MARCO MUOZ DORALIS ACOSTA MENDO"}, {"MATRÍCULA CT": "X000475", "NIU": 21441427, "NIS_RAD_1": 486361, "NIC": 1354210.0, "MEDIDOR": "1069630-MCA47", "DIRECCION_CLIENTE": "CL 85  No. CR 78D -  26", "NOMBRE_CLIENTE": "MARTHA ISABEL ROJAS PUELLO"}, {"MATRÍCULA CT": "X000475", "NIU": 21441488, "NIS_RAD_1": 486434, "NIC": "", "MEDIDOR": "", "DIRECCION_CLIENTE": "CL 85  No. CR 78D -  26", "NOMBRE_CLIENTE": ""}, {"MATRÍCULA CT": "X000475", "NIU": 21441507, "NIS_RAD_1": 486453, "NIC": 1354132.0, "MEDIDOR": "1069615-MCA47", "DIRECCION_CLIENTE": "CL 85  No. CR 78D -  26", "NOMBRE_CLIENTE": "ERNESTO RAFAEL HERRERA DIAZ GRANADO"}, {"MATRÍCULA CT": "X000475", "NIU": 21441468, "NIS_RAD_1": 486410, "NIC": 1354238.0, "MEDIDOR": "1069735-MCA47", "DIRECCION_CLIENTE": "CL 85  No. CR 78D -  26", "NOMBRE_CLIENTE": "INIRIDA CONCEPCION AVENDAO VILLA"}, {"MATRÍCULA CT": "X000475", "NIU": 21441438, "NIS_RAD_1": 486377, "NIC": 1354215.0, "MEDIDOR": "1069576-MCA47", "DIRECCION_CLIENTE": "CL 85  No. CR 78D -  26", "NOMBRE_CLIENTE": "LIZZTE LUCILA CAMARGO"}, {"MATRÍCULA CT": "X000475", "NIU": 21442150, "NIS_RAD_1": 487854, "NIC": "", "MEDIDOR": "", "DIRECCION_CLIENTE": "CL 85  No. CR 78D -  26", "NOMBRE_CLIENTE": ""}, {"MATRÍCULA CT": "X000475", "NIU": 21442157, "NIS_RAD_1": 487863, "NIC": "", "MEDIDOR": "", "DIRECCION_CLIENTE": "CL 85  No. CR 78D -  26", "NOMBRE_CLIENTE": ""}, {"MATRÍCULA CT": "X000475", "NIU": 21441550, "NIS_RAD_1": 486511, "NIC": 1354184.0, "MEDIDOR": "1069755-MCA47", "DIRECCION_CLIENTE": "CL 85  No. CR 78D -  26", "NOMBRE_CLIENTE": "Sin definir JAVIER FONTALVO BUEL"}, {"MATRÍCULA CT": "X000475", "NIU": 21441539, "NIS_RAD_1": 486496, "NIC": 1354151.0, "MEDIDOR": "1069614-MCA47", "DIRECCION_CLIENTE": "CL 85  No. CR 78D -  26", "NOMBRE_CLIENTE": "ANDREA CAROLINA NUCCI CORTES"}, {"MATRÍCULA CT": "X000475", "NIU": 21441519, "NIS_RAD_1": 486466, "NIC": 1354077.0, "MEDIDOR": "1069695-MCA47", "DIRECCION_CLIENTE": "CL 85  No. CR 78D -  26", "NOMBRE_CLIENTE": "LEIVIS DEL CARMEN FLOREZ VARGAS"}, {"MATRÍCULA CT": "X000475", "NIU": 21441493, "NIS_RAD_1": 486439, "NIC": 1354060.0, "MEDIDOR": "1069678-MCA47", "DIRECCION_CLIENTE": "CL 85  No. CR 78D -  26", "NOMBRE_CLIENTE": "DIEGO RESTREPO JIMENEZ"}, {"MATRÍCULA CT": "X000475", "NIU": 21441457, "NIS_RAD_1": 486399, "NIC": 1354230.0, "MEDIDOR": "1069637-MCA47", "DIRECCION_CLIENTE": "CL 85  No. CR 78D -  26", "NOMBRE_CLIENTE": "ARMANDO SEGUNDO CHACON PUERTAS"}, {"MATRÍCULA CT": "X000475", "NIU": 21442153, "NIS_RAD_1": 487859, "NIC": "", "MEDIDOR": "", "DIRECCION_CLIENTE": "CL 85  No. CR 78D -  26", "NOMBRE_CLIENTE": ""}, {"MATRÍCULA CT": "X000475", "NIU": 21442154, "NIS_RAD_1": 487860, "NIC": 1354250.0, "MEDIDOR": "1069704-MCA47", "DIRECCION_CLIENTE": "CL 85  No. CR 78D -  26", "NOMBRE_CLIENTE": "WILLIAM ENRIQUE OCHOA MORENO"}, {"MATRÍCULA CT": "X000475", "NIU": 21441448, "NIS_RAD_1": 486387, "NIC": 1354042.0, "MEDIDOR": "1069669-MCA47", "DIRECCION_CLIENTE": "CL 85  No. CR 78D -  26", "NOMBRE_CLIENTE": "CINDY CASALING"}, {"MATRÍCULA CT": "X000475", "NIU": 21441501, "NIS_RAD_1": 486447, "NIC": 1354065.0, "MEDIDOR": "1069690-MCA47", "DIRECCION_CLIENTE": "CL 85  No. CR 78D -  26", "NOMBRE_CLIENTE": "GHISAYS EDITH BARRIOS HURTADO"}, {"MATRÍCULA CT": "X000475", "NIU": 21441552, "NIS_RAD_1": 486513, "NIC": 1354148.0, "MEDIDOR": "1069583-MCA47", "DIRECCION_CLIENTE": "CL 85  No. CR 78D -  26", "NOMBRE_CLIENTE": "ALCIDIADES JOSE ANDION CAMPO"}], "TOTAL_CLIENTES": 131}